{
  "domain": "bankujesz.pl",
  "endpoint": "get_backlinks_anchor_data",
  "data": {
    "ok": true,
    "data": [
      {
        "link_domain": "bankujesz.pl",
        "is_main_domain": true,
        "anchor": "Historia Santander Bank Polska",
        "anchor_type": [],
        "count": {
          "count": 121,
          "percent_of_total": 0.019839317920970653
        },
        "domains_with_anchor_count": 1,
        "anchors_uniq_count": 120,
        "percent_of_total": 0.019839317920970653
      },
      {
        "link_domain": "bankujesz.pl",
        "is_main_domain": true,
        "anchor": "kontakt Santander Bank Polska",
        "anchor_type": [],
        "count": {
          "count": 121,
          "percent_of_total": 0.019839317920970653
        },
        "domains_with_anchor_count": 1,
        "anchors_uniq_count": 120,
        "percent_of_total": 0.019839317920970653
      },
      {
        "link_domain": "bankujesz.pl",
        "is_main_domain": true,
        "anchor": "Konto bankowe w Santander Bank Polska",
        "anchor_type": [],
        "count": {
          "count": 121,
          "percent_of_total": 0.019839317920970653
        },
        "domains_with_anchor_count": 1,
        "anchors_uniq_count": 120,
        "percent_of_total": 0.019839317920970653
      },
      {
        "link_domain": "bankujesz.pl",
        "is_main_domain": true,
        "anchor": "Godziny przelewów wychodzących i przelewów przychodzących w Santander Bank Polska",
        "anchor_type": [],
        "count": {
          "count": 121,
          "percent_of_total": 0.019839317920970653
        },
        "domains_with_anchor_count": 1,
        "anchors_uniq_count": 120,
        "percent_of_total": 0.019839317920970653
      },
      {
        "link_domain": "bankujesz.pl",
        "is_main_domain": true,
        "anchor": "Główna siedziba banku Santrander",
        "anchor_type": [],
        "count": {
          "count": 121,
          "percent_of_total": 0.019839317920970653
        },
        "domains_with_anchor_count": 1,
        "anchors_uniq_count": 120,
        "percent_of_total": 0.019839317920970653
      },
      {
        "link_domain": "bankujesz.pl",
        "is_main_domain": true,
        "anchor": "kont oszczędnościowych",
        "anchor_type": [],
        "count": {
          "count": 111,
          "percent_of_total": 0.01819970486965076
        },
        "domains_with_anchor_count": 1,
        "anchors_uniq_count": 110,
        "percent_of_total": 0.01819970486965076
      },
      {
        "link_domain": "bankujesz.pl",
        "is_main_domain": true,
        "anchor": "Kontakt Pekao SA",
        "anchor_type": [],
        "count": {
          "count": 101,
          "percent_of_total": 0.016560091818330874
        },
        "domains_with_anchor_count": 1,
        "anchors_uniq_count": 98,
        "percent_of_total": 0.016560091818330874
      },
      {
        "link_domain": "bankujesz.pl",
        "is_main_domain": true,
        "anchor": "Siedziba Banku Pekao S.A.",
        "anchor_type": [],
        "count": {
          "count": 101,
          "percent_of_total": 0.016560091818330874
        },
        "domains_with_anchor_count": 1,
        "anchors_uniq_count": 98,
        "percent_of_total": 0.016560091818330874
      },
      {
        "link_domain": "bankujesz.pl",
        "is_main_domain": true,
        "anchor": "przelewach wychodzących i przychodzących oraz sesjach elixir w Banku Pekao S.A",
        "anchor_type": [],
        "count": {
          "count": 101,
          "percent_of_total": 0.016560091818330874
        },
        "domains_with_anchor_count": 1,
        "anchors_uniq_count": 98,
        "percent_of_total": 0.016560091818330874
      },
      {
        "link_domain": "bankujesz.pl",
        "is_main_domain": true,
        "anchor": "Ciekawostki dotyczące Banku Pekao S.A.",
        "anchor_type": [],
        "count": {
          "count": 101,
          "percent_of_total": 0.016560091818330874
        },
        "domains_with_anchor_count": 1,
        "anchors_uniq_count": 98,
        "percent_of_total": 0.016560091818330874
      },
      {
        "link_domain": "bankujesz.pl",
        "is_main_domain": true,
        "anchor": "Konto walutowe",
        "anchor_type": [],
        "count": {
          "count": 100,
          "percent_of_total": 0.016396130513198885
        },
        "domains_with_anchor_count": 1,
        "anchors_uniq_count": 100,
        "percent_of_total": 0.016396130513198885
      },
      {
        "link_domain": "bankujesz.pl",
        "is_main_domain": true,
        "anchor": "Główna siedziba Alior Bank",
        "anchor_type": [],
        "count": {
          "count": 97,
          "percent_of_total": 0.01590424659780292
        },
        "domains_with_anchor_count": 1,
        "anchors_uniq_count": 94,
        "percent_of_total": 0.01590424659780292
      },
      {
        "link_domain": "bankujesz.pl",
        "is_main_domain": true,
        "anchor": "Alior Bank ciekawostki",
        "anchor_type": [],
        "count": {
          "count": 97,
          "percent_of_total": 0.01590424659780292
        },
        "domains_with_anchor_count": 1,
        "anchors_uniq_count": 94,
        "percent_of_total": 0.01590424659780292
      },
      {
        "link_domain": "bankujesz.pl",
        "is_main_domain": true,
        "anchor": "Konto jakże osobiste",
        "anchor_type": [],
        "count": {
          "count": 97,
          "percent_of_total": 0.01590424659780292
        },
        "domains_with_anchor_count": 1,
        "anchors_uniq_count": 94,
        "percent_of_total": 0.01590424659780292
      },
      {
        "link_domain": "bankujesz.pl",
        "is_main_domain": true,
        "anchor": "Godziny przelewów wychodzących i przychodzących w Alior Banku.",
        "anchor_type": [],
        "count": {
          "count": 97,
          "percent_of_total": 0.01590424659780292
        },
        "domains_with_anchor_count": 1,
        "anchors_uniq_count": 94,
        "percent_of_total": 0.01590424659780292
      },
      {
        "link_domain": "bankujesz.pl",
        "is_main_domain": true,
        "anchor": "Historia Alior Bank",
        "anchor_type": [],
        "count": {
          "count": 97,
          "percent_of_total": 0.01590424659780292
        },
        "domains_with_anchor_count": 1,
        "anchors_uniq_count": 94,
        "percent_of_total": 0.01590424659780292
      },
      {
        "link_domain": "bankujesz.pl",
        "is_main_domain": true,
        "anchor": "Alior Giełda",
        "anchor_type": [],
        "count": {
          "count": 97,
          "percent_of_total": 0.01590424659780292
        },
        "domains_with_anchor_count": 1,
        "anchors_uniq_count": 94,
        "percent_of_total": 0.01590424659780292
      },
      {
        "link_domain": "bankujesz.pl",
        "is_main_domain": true,
        "anchor": "",
        "anchor_type": [
          "multimedia"
        ],
        "count": {
          "count": 96,
          "percent_of_total": 0.01574028529267093
        },
        "domains_with_anchor_count": 13,
        "anchors_uniq_count": 58,
        "percent_of_total": 0.01574028529267093
      },
      {
        "link_domain": "bankujesz.pl",
        "is_main_domain": true,
        "anchor": "Kantory internetowe",
        "anchor_type": [],
        "count": {
          "count": 81,
          "percent_of_total": 0.013280865715691098
        },
        "domains_with_anchor_count": 1,
        "anchors_uniq_count": 81,
        "percent_of_total": 0.013280865715691098
      },
      {
        "link_domain": "bankujesz.pl",
        "is_main_domain": true,
        "anchor": "Miejsce III eMakler",
        "anchor_type": [],
        "count": {
          "count": 76,
          "percent_of_total": 0.012461059190031152
        },
        "domains_with_anchor_count": 1,
        "anchors_uniq_count": 76,
        "percent_of_total": 0.012461059190031152
      },
      {
        "link_domain": "bankujesz.pl",
        "is_main_domain": true,
        "anchor": "Miejsce II Bossa",
        "anchor_type": [],
        "count": {
          "count": 76,
          "percent_of_total": 0.012461059190031152
        },
        "domains_with_anchor_count": 1,
        "anchors_uniq_count": 76,
        "percent_of_total": 0.012461059190031152
      },
      {
        "link_domain": "bankujesz.pl",
        "is_main_domain": true,
        "anchor": "Zobacz pełny ranking ofert!",
        "anchor_type": [],
        "count": {
          "count": 76,
          "percent_of_total": 0.012461059190031152
        },
        "domains_with_anchor_count": 1,
        "anchors_uniq_count": 76,
        "percent_of_total": 0.012461059190031152
      },
      {
        "link_domain": "bankujesz.pl",
        "is_main_domain": true,
        "anchor": "rankingiem kont osobistych na listopad 2023",
        "anchor_type": [],
        "count": {
          "count": 74,
          "percent_of_total": 0.012133136579767174
        },
        "domains_with_anchor_count": 1,
        "anchors_uniq_count": 74,
        "percent_of_total": 0.012133136579767174
      },
      {
        "link_domain": "bankujesz.pl",
        "is_main_domain": true,
        "anchor": "Buy Now, Pay Later&quot;",
        "anchor_type": [],
        "count": {
          "count": 70,
          "percent_of_total": 0.011477291359239219
        },
        "domains_with_anchor_count": 1,
        "anchors_uniq_count": 70,
        "percent_of_total": 0.011477291359239219
      },
      {
        "link_domain": "bankujesz.pl",
        "is_main_domain": true,
        "anchor": "Ranking kredytów dla firm styczeń 2024",
        "anchor_type": [],
        "count": {
          "count": 65,
          "percent_of_total": 0.010657484833579275
        },
        "domains_with_anchor_count": 1,
        "anchors_uniq_count": 65,
        "percent_of_total": 0.010657484833579275
      },
      {
        "link_domain": "bankujesz.pl",
        "is_main_domain": true,
        "anchor": "Buy Now, Pay Later",
        "anchor_type": [],
        "count": {
          "count": 65,
          "percent_of_total": 0.010657484833579275
        },
        "domains_with_anchor_count": 1,
        "anchors_uniq_count": 64,
        "percent_of_total": 0.010657484833579275
      },
      {
        "link_domain": "bankujesz.pl",
        "is_main_domain": true,
        "anchor": "tego",
        "anchor_type": [],
        "count": {
          "count": 65,
          "percent_of_total": 0.010657484833579275
        },
        "domains_with_anchor_count": 1,
        "anchors_uniq_count": 65,
        "percent_of_total": 0.010657484833579275
      },
      {
        "link_domain": "bankujesz.pl",
        "is_main_domain": true,
        "anchor": "Miejsce I Nest Bank",
        "anchor_type": [],
        "count": {
          "count": 65,
          "percent_of_total": 0.010657484833579275
        },
        "domains_with_anchor_count": 1,
        "anchors_uniq_count": 65,
        "percent_of_total": 0.010657484833579275
      },
      {
        "link_domain": "bankujesz.pl",
        "is_main_domain": true,
        "anchor": "BNPL psychologiczną pułapką dla zakupoholików? Kontrowersje wokół kup teraz, zapłać później",
        "anchor_type": [],
        "count": {
          "count": 65,
          "percent_of_total": 0.010657484833579275
        },
        "domains_with_anchor_count": 1,
        "anchors_uniq_count": 64,
        "percent_of_total": 0.010657484833579275
      },
      {
        "link_domain": "bankujesz.pl",
        "is_main_domain": true,
        "anchor": "Kup Teraz, Zapłać Później",
        "anchor_type": [],
        "count": {
          "count": 65,
          "percent_of_total": 0.010657484833579275
        },
        "domains_with_anchor_count": 1,
        "anchors_uniq_count": 64,
        "percent_of_total": 0.010657484833579275
      },
      {
        "link_domain": "bankujesz.pl",
        "is_main_domain": true,
        "anchor": "Miejsce II Alior Bank",
        "anchor_type": [],
        "count": {
          "count": 65,
          "percent_of_total": 0.010657484833579275
        },
        "domains_with_anchor_count": 1,
        "anchors_uniq_count": 65,
        "percent_of_total": 0.010657484833579275
      },
      {
        "link_domain": "bankujesz.pl",
        "is_main_domain": true,
        "anchor": "Konto Maklerskie eMakler",
        "anchor_type": [],
        "count": {
          "count": 61,
          "percent_of_total": 0.01000163961305132
        },
        "domains_with_anchor_count": 1,
        "anchors_uniq_count": 59,
        "percent_of_total": 0.01000163961305132
      },
      {
        "link_domain": "bankujesz.pl",
        "is_main_domain": true,
        "anchor": "onto Maklerskie BOSSA",
        "anchor_type": [],
        "count": {
          "count": 61,
          "percent_of_total": 0.01000163961305132
        },
        "domains_with_anchor_count": 1,
        "anchors_uniq_count": 59,
        "percent_of_total": 0.01000163961305132
      },
      {
        "link_domain": "bankujesz.pl",
        "is_main_domain": true,
        "anchor": "Ranking kont osobistych",
        "anchor_type": [],
        "count": {
          "count": 61,
          "percent_of_total": 0.01000163961305132
        },
        "domains_with_anchor_count": 1,
        "anchors_uniq_count": 61,
        "percent_of_total": 0.01000163961305132
      },
      {
        "link_domain": "bankujesz.pl",
        "is_main_domain": true,
        "anchor": "Konto Maklerskie XTB",
        "anchor_type": [],
        "count": {
          "count": 61,
          "percent_of_total": 0.01000163961305132
        },
        "domains_with_anchor_count": 1,
        "anchors_uniq_count": 59,
        "percent_of_total": 0.01000163961305132
      },
      {
        "link_domain": "bankujesz.pl",
        "is_main_domain": true,
        "anchor": "Najlepiej oprocentowane rachunki oszczędnościowe",
        "anchor_type": [],
        "count": {
          "count": 58,
          "percent_of_total": 0.009509755697655354
        },
        "domains_with_anchor_count": 1,
        "anchors_uniq_count": 58,
        "percent_of_total": 0.009509755697655354
      },
      {
        "link_domain": "bankujesz.pl",
        "is_main_domain": true,
        "anchor": "Karta kredytowa Citi Handlowy",
        "anchor_type": [],
        "count": {
          "count": 58,
          "percent_of_total": 0.009509755697655354
        },
        "domains_with_anchor_count": 1,
        "anchors_uniq_count": 58,
        "percent_of_total": 0.009509755697655354
      },
      {
        "link_domain": "bankujesz.pl",
        "is_main_domain": true,
        "anchor": "Karta kredytowa BNP Paribas",
        "anchor_type": [],
        "count": {
          "count": 58,
          "percent_of_total": 0.009509755697655354
        },
        "domains_with_anchor_count": 1,
        "anchors_uniq_count": 58,
        "percent_of_total": 0.009509755697655354
      },
      {
        "link_domain": "bankujesz.pl",
        "is_main_domain": true,
        "anchor": "Karta kredytowa Pekao SA",
        "anchor_type": [],
        "count": {
          "count": 58,
          "percent_of_total": 0.009509755697655354
        },
        "domains_with_anchor_count": 1,
        "anchors_uniq_count": 58,
        "percent_of_total": 0.009509755697655354
      },
      {
        "link_domain": "bankujesz.pl",
        "is_main_domain": true,
        "anchor": "Karta kredytowa Santander",
        "anchor_type": [],
        "count": {
          "count": 58,
          "percent_of_total": 0.009509755697655354
        },
        "domains_with_anchor_count": 1,
        "anchors_uniq_count": 58,
        "percent_of_total": 0.009509755697655354
      },
      {
        "link_domain": "bankujesz.pl",
        "is_main_domain": true,
        "anchor": "rankingiem kont maklerskich",
        "anchor_type": [],
        "count": {
          "count": 57,
          "percent_of_total": 0.009345794392523364
        },
        "domains_with_anchor_count": 1,
        "anchors_uniq_count": 56,
        "percent_of_total": 0.009345794392523364
      },
      {
        "link_domain": "bankujesz.pl",
        "is_main_domain": true,
        "anchor": "Co to jest BIK?",
        "anchor_type": [],
        "count": {
          "count": 54,
          "percent_of_total": 0.008853910477127398
        },
        "domains_with_anchor_count": 1,
        "anchors_uniq_count": 53,
        "percent_of_total": 0.008853910477127398
      },
      {
        "link_domain": "bankujesz.pl",
        "is_main_domain": true,
        "anchor": "kantor internetowy",
        "anchor_type": [],
        "count": {
          "count": 54,
          "percent_of_total": 0.008853910477127398
        },
        "domains_with_anchor_count": 1,
        "anchors_uniq_count": 54,
        "percent_of_total": 0.008853910477127398
      },
      {
        "link_domain": "bankujesz.pl",
        "is_main_domain": true,
        "anchor": "historia mBanku",
        "anchor_type": [],
        "count": {
          "count": 53,
          "percent_of_total": 0.00868994917199541
        },
        "domains_with_anchor_count": 1,
        "anchors_uniq_count": 52,
        "percent_of_total": 0.00868994917199541
      },
      {
        "link_domain": "bankujesz.pl",
        "is_main_domain": true,
        "anchor": "Godziny przelewów wychodzących i przychodzących w mBanku.",
        "anchor_type": [],
        "count": {
          "count": 53,
          "percent_of_total": 0.00868994917199541
        },
        "domains_with_anchor_count": 1,
        "anchors_uniq_count": 52,
        "percent_of_total": 0.00868994917199541
      },
      {
        "link_domain": "bankujesz.pl",
        "is_main_domain": true,
        "anchor": "Główna siedziba mBank",
        "anchor_type": [],
        "count": {
          "count": 53,
          "percent_of_total": 0.00868994917199541
        },
        "domains_with_anchor_count": 1,
        "anchors_uniq_count": 52,
        "percent_of_total": 0.00868994917199541
      },
      {
        "link_domain": "bankujesz.pl",
        "is_main_domain": true,
        "anchor": "Prezesem mBanku",
        "anchor_type": [],
        "count": {
          "count": 53,
          "percent_of_total": 0.00868994917199541
        },
        "domains_with_anchor_count": 1,
        "anchors_uniq_count": 52,
        "percent_of_total": 0.00868994917199541
      },
      {
        "link_domain": "bankujesz.pl",
        "is_main_domain": true,
        "anchor": "Ranking lokat 6 miesięcznych październik 2023",
        "anchor_type": [],
        "count": {
          "count": 52,
          "percent_of_total": 0.00852598786686342
        },
        "domains_with_anchor_count": 1,
        "anchors_uniq_count": 50,
        "percent_of_total": 0.00852598786686342
      },
      {
        "link_domain": "bankujesz.pl",
        "is_main_domain": true,
        "anchor": "Miejsce III Bank Pekao",
        "anchor_type": [],
        "count": {
          "count": 52,
          "percent_of_total": 0.00852598786686342
        },
        "domains_with_anchor_count": 1,
        "anchors_uniq_count": 52,
        "percent_of_total": 0.00852598786686342
      },
      {
        "link_domain": "bankujesz.pl",
        "is_main_domain": true,
        "anchor": "Ranking lokat 12 miesięcznych październik 2023",
        "anchor_type": [],
        "count": {
          "count": 52,
          "percent_of_total": 0.00852598786686342
        },
        "domains_with_anchor_count": 1,
        "anchors_uniq_count": 50,
        "percent_of_total": 0.00852598786686342
      },
      {
        "link_domain": "bankujesz.pl",
        "is_main_domain": true,
        "anchor": "Ranking lokat 3 miesięcznych październik 2023",
        "anchor_type": [],
        "count": {
          "count": 52,
          "percent_of_total": 0.00852598786686342
        },
        "domains_with_anchor_count": 1,
        "anchors_uniq_count": 50,
        "percent_of_total": 0.00852598786686342
      },
      {
        "link_domain": "bankujesz.pl",
        "is_main_domain": true,
        "anchor": "Ranking kont dla młodych styczeń 2024",
        "anchor_type": [],
        "count": {
          "count": 52,
          "percent_of_total": 0.00852598786686342
        },
        "domains_with_anchor_count": 1,
        "anchors_uniq_count": 52,
        "percent_of_total": 0.00852598786686342
      },
      {
        "link_domain": "bankujesz.pl",
        "is_main_domain": true,
        "anchor": "Ranking kont oszczędnościowych wrzesień 2023",
        "anchor_type": [],
        "count": {
          "count": 52,
          "percent_of_total": 0.00852598786686342
        },
        "domains_with_anchor_count": 1,
        "anchors_uniq_count": 52,
        "percent_of_total": 0.00852598786686342
      },
      {
        "link_domain": "bankujesz.pl",
        "is_main_domain": true,
        "anchor": "Miejsce II mBank",
        "anchor_type": [],
        "count": {
          "count": 52,
          "percent_of_total": 0.00852598786686342
        },
        "domains_with_anchor_count": 1,
        "anchors_uniq_count": 52,
        "percent_of_total": 0.00852598786686342
      },
      {
        "link_domain": "bankujesz.pl",
        "is_main_domain": true,
        "anchor": "Miejsce I PKO BP",
        "anchor_type": [],
        "count": {
          "count": 52,
          "percent_of_total": 0.00852598786686342
        },
        "domains_with_anchor_count": 1,
        "anchors_uniq_count": 52,
        "percent_of_total": 0.00852598786686342
      },
      {
        "link_domain": "bankujesz.pl",
        "is_main_domain": true,
        "anchor": "Ranking lokat 6 miesięcznych",
        "anchor_type": [],
        "count": {
          "count": 51,
          "percent_of_total": 0.008362026561731432
        },
        "domains_with_anchor_count": 1,
        "anchors_uniq_count": 48,
        "percent_of_total": 0.008362026561731432
      },
      {
        "link_domain": "bankujesz.pl",
        "is_main_domain": true,
        "anchor": "Kup teraz, zapłać później. Jakie firmy na polskim rynku oferują odroczone płatności? Zestawienie ofert na listopad 2023. Najlepszy usługodawca w dziedzinie odroczone płatności",
        "anchor_type": [],
        "count": {
          "count": 50,
          "percent_of_total": 0.008198065256599442
        },
        "domains_with_anchor_count": 1,
        "anchors_uniq_count": 50,
        "percent_of_total": 0.008198065256599442
      },
      {
        "link_domain": "bankujesz.pl",
        "is_main_domain": true,
        "anchor": "Ranking lokat 1 miesięcznych październik 2023",
        "anchor_type": [],
        "count": {
          "count": 45,
          "percent_of_total": 0.0073782587309394985
        },
        "domains_with_anchor_count": 1,
        "anchors_uniq_count": 43,
        "percent_of_total": 0.0073782587309394985
      },
      {
        "link_domain": "bankujesz.pl",
        "is_main_domain": true,
        "anchor": "Lokata 6 miesięczna Inbank",
        "anchor_type": [],
        "count": {
          "count": 44,
          "percent_of_total": 0.00721429742580751
        },
        "domains_with_anchor_count": 1,
        "anchors_uniq_count": 44,
        "percent_of_total": 0.00721429742580751
      },
      {
        "link_domain": "bankujesz.pl",
        "is_main_domain": true,
        "anchor": "Lokata 6 miesięczna BFF",
        "anchor_type": [],
        "count": {
          "count": 44,
          "percent_of_total": 0.00721429742580751
        },
        "domains_with_anchor_count": 1,
        "anchors_uniq_count": 44,
        "percent_of_total": 0.00721429742580751
      },
      {
        "link_domain": "bankujesz.pl",
        "is_main_domain": true,
        "anchor": "Konto firmowe",
        "anchor_type": [],
        "count": {
          "count": 42,
          "percent_of_total": 0.006886374815543532
        },
        "domains_with_anchor_count": 1,
        "anchors_uniq_count": 41,
        "percent_of_total": 0.006886374815543532
      },
      {
        "link_domain": "bankujesz.pl",
        "is_main_domain": true,
        "anchor": "Ranking giełd kryptowalut listopad 2023",
        "anchor_type": [],
        "count": {
          "count": 41,
          "percent_of_total": 0.006722413510411543
        },
        "domains_with_anchor_count": 1,
        "anchors_uniq_count": 39,
        "percent_of_total": 0.006722413510411543
      },
      {
        "link_domain": "bankujesz.pl",
        "is_main_domain": true,
        "anchor": "konsolidacja",
        "anchor_type": [],
        "count": {
          "count": 40,
          "percent_of_total": 0.006558452205279554
        },
        "domains_with_anchor_count": 1,
        "anchors_uniq_count": 40,
        "percent_of_total": 0.006558452205279554
      },
      {
        "link_domain": "bankujesz.pl",
        "is_main_domain": true,
        "anchor": "konta oszczędnościowe",
        "anchor_type": [],
        "count": {
          "count": 39,
          "percent_of_total": 0.006394490900147565
        },
        "domains_with_anchor_count": 1,
        "anchors_uniq_count": 39,
        "percent_of_total": 0.006394490900147565
      },
      {
        "link_domain": "bankujesz.pl",
        "is_main_domain": true,
        "anchor": "lokat 6-miesięcznych na październik",
        "anchor_type": [],
        "count": {
          "count": 38,
          "percent_of_total": 0.006230529595015576
        },
        "domains_with_anchor_count": 1,
        "anchors_uniq_count": 38,
        "percent_of_total": 0.006230529595015576
      },
      {
        "link_domain": "bankujesz.pl",
        "is_main_domain": true,
        "anchor": "Ranking kont oszczędnościowych listopad 2023",
        "anchor_type": [],
        "count": {
          "count": 38,
          "percent_of_total": 0.006230529595015576
        },
        "domains_with_anchor_count": 1,
        "anchors_uniq_count": 38,
        "percent_of_total": 0.006230529595015576
      },
      {
        "link_domain": "bankujesz.pl",
        "is_main_domain": true,
        "anchor": "Ranking 3 miesięcznych lokat bankowych",
        "anchor_type": [],
        "count": {
          "count": 37,
          "percent_of_total": 0.006066568289883587
        },
        "domains_with_anchor_count": 1,
        "anchors_uniq_count": 35,
        "percent_of_total": 0.006066568289883587
      },
      {
        "link_domain": "bankujesz.pl",
        "is_main_domain": true,
        "anchor": "Ranking 6 miesięcznych lokat bankowych",
        "anchor_type": [],
        "count": {
          "count": 37,
          "percent_of_total": 0.006066568289883587
        },
        "domains_with_anchor_count": 1,
        "anchors_uniq_count": 35,
        "percent_of_total": 0.006066568289883587
      },
      {
        "link_domain": "bankujesz.pl",
        "is_main_domain": true,
        "anchor": "Ranking 12 miesięcznych lokat bankowych",
        "anchor_type": [],
        "count": {
          "count": 37,
          "percent_of_total": 0.006066568289883587
        },
        "domains_with_anchor_count": 1,
        "anchors_uniq_count": 35,
        "percent_of_total": 0.006066568289883587
      },
      {
        "link_domain": "bankujesz.pl",
        "is_main_domain": true,
        "anchor": "Ranking lokat 6 miesięcznych na styczeń 2024",
        "anchor_type": [],
        "count": {
          "count": 34,
          "percent_of_total": 0.0055746843744876205
        },
        "domains_with_anchor_count": 1,
        "anchors_uniq_count": 34,
        "percent_of_total": 0.0055746843744876205
      },
      {
        "link_domain": "bankujesz.pl",
        "is_main_domain": true,
        "anchor": "Miejsce II Lokata 6 miesięczna Velo Bank",
        "anchor_type": [],
        "count": {
          "count": 34,
          "percent_of_total": 0.0055746843744876205
        },
        "domains_with_anchor_count": 1,
        "anchors_uniq_count": 34,
        "percent_of_total": 0.0055746843744876205
      },
      {
        "link_domain": "bankujesz.pl",
        "is_main_domain": true,
        "anchor": "BNP Paribas",
        "anchor_type": [],
        "count": {
          "count": 34,
          "percent_of_total": 0.0055746843744876205
        },
        "domains_with_anchor_count": 1,
        "anchors_uniq_count": 34,
        "percent_of_total": 0.0055746843744876205
      },
      {
        "link_domain": "bankujesz.pl",
        "is_main_domain": true,
        "anchor": "anking kredytów konsolidacyjnych wrzesień 2023",
        "anchor_type": [],
        "count": {
          "count": 33,
          "percent_of_total": 0.0054107230693556324
        },
        "domains_with_anchor_count": 1,
        "anchors_uniq_count": 33,
        "percent_of_total": 0.0054107230693556324
      },
      {
        "link_domain": "bankujesz.pl",
        "is_main_domain": true,
        "anchor": "Miejsce 2 Konto Walutowe mBank",
        "anchor_type": [],
        "count": {
          "count": 32,
          "percent_of_total": 0.0052467617642236435
        },
        "domains_with_anchor_count": 1,
        "anchors_uniq_count": 32,
        "percent_of_total": 0.0052467617642236435
      },
      {
        "link_domain": "bankujesz.pl",
        "is_main_domain": true,
        "anchor": "Zobacz ranking kantorów internetowych listopad 2023",
        "anchor_type": [],
        "count": {
          "count": 32,
          "percent_of_total": 0.0052467617642236435
        },
        "domains_with_anchor_count": 1,
        "anchors_uniq_count": 32,
        "percent_of_total": 0.0052467617642236435
      },
      {
        "link_domain": "bankujesz.pl",
        "is_main_domain": true,
        "anchor": "Miejsce 1 Konto Walutowe Alior Bank",
        "anchor_type": [],
        "count": {
          "count": 32,
          "percent_of_total": 0.0052467617642236435
        },
        "domains_with_anchor_count": 1,
        "anchors_uniq_count": 32,
        "percent_of_total": 0.0052467617642236435
      },
      {
        "link_domain": "bankujesz.pl",
        "is_main_domain": true,
        "anchor": "Miejsce 3 Konto Walutowe PKO BP",
        "anchor_type": [],
        "count": {
          "count": 32,
          "percent_of_total": 0.0052467617642236435
        },
        "domains_with_anchor_count": 1,
        "anchors_uniq_count": 32,
        "percent_of_total": 0.0052467617642236435
      },
      {
        "link_domain": "bankujesz.pl",
        "is_main_domain": true,
        "anchor": "Ranking lokat 12 miesięcznych",
        "anchor_type": [],
        "count": {
          "count": 32,
          "percent_of_total": 0.0052467617642236435
        },
        "domains_with_anchor_count": 1,
        "anchors_uniq_count": 30,
        "percent_of_total": 0.0052467617642236435
      },
      {
        "link_domain": "bankujesz.pl",
        "is_main_domain": true,
        "anchor": "Ranking kont walutowych listopad 2023",
        "anchor_type": [],
        "count": {
          "count": 32,
          "percent_of_total": 0.0052467617642236435
        },
        "domains_with_anchor_count": 1,
        "anchors_uniq_count": 32,
        "percent_of_total": 0.0052467617642236435
      },
      {
        "link_domain": "bankujesz.pl",
        "is_main_domain": true,
        "anchor": "Lokaty bankowe",
        "anchor_type": [],
        "count": {
          "count": 31,
          "percent_of_total": 0.005082800459091655
        },
        "domains_with_anchor_count": 1,
        "anchors_uniq_count": 29,
        "percent_of_total": 0.005082800459091655
      },
      {
        "link_domain": "bankujesz.pl",
        "is_main_domain": true,
        "anchor": "Lokata terminowa",
        "anchor_type": [],
        "count": {
          "count": 31,
          "percent_of_total": 0.005082800459091655
        },
        "domains_with_anchor_count": 1,
        "anchors_uniq_count": 29,
        "percent_of_total": 0.005082800459091655
      },
      {
        "link_domain": "bankujesz.pl",
        "is_main_domain": true,
        "anchor": "Ranking kont oszczędnościowych- grudzień 2022",
        "anchor_type": [],
        "count": {
          "count": 31,
          "percent_of_total": 0.005082800459091655
        },
        "domains_with_anchor_count": 1,
        "anchors_uniq_count": 31,
        "percent_of_total": 0.005082800459091655
      },
      {
        "link_domain": "bankujesz.pl",
        "is_main_domain": true,
        "anchor": "Ranking lokat 3 miesięcznych",
        "anchor_type": [],
        "count": {
          "count": 30,
          "percent_of_total": 0.004918839153959666
        },
        "domains_with_anchor_count": 1,
        "anchors_uniq_count": 28,
        "percent_of_total": 0.004918839153959666
      },
      {
        "link_domain": "bankujesz.pl",
        "is_main_domain": true,
        "anchor": "BANKUJESZ.PL",
        "anchor_type": [],
        "count": {
          "count": 29,
          "percent_of_total": 0.004754877848827677
        },
        "domains_with_anchor_count": 1,
        "anchors_uniq_count": 29,
        "percent_of_total": 0.004754877848827677
      },
      {
        "link_domain": "bankujesz.pl",
        "is_main_domain": true,
        "anchor": "Miejsce IV Etoro",
        "anchor_type": [],
        "count": {
          "count": 28,
          "percent_of_total": 0.004590916543695688
        },
        "domains_with_anchor_count": 1,
        "anchors_uniq_count": 28,
        "percent_of_total": 0.004590916543695688
      },
      {
        "link_domain": "bankujesz.pl",
        "is_main_domain": true,
        "anchor": "Miejsce I XTB",
        "anchor_type": [],
        "count": {
          "count": 28,
          "percent_of_total": 0.004590916543695688
        },
        "domains_with_anchor_count": 1,
        "anchors_uniq_count": 28,
        "percent_of_total": 0.004590916543695688
      },
      {
        "link_domain": "bankujesz.pl",
        "is_main_domain": true,
        "anchor": "Oprocentowanie lokat",
        "anchor_type": [],
        "count": {
          "count": 28,
          "percent_of_total": 0.004590916543695688
        },
        "domains_with_anchor_count": 1,
        "anchors_uniq_count": 28,
        "percent_of_total": 0.004590916543695688
      },
      {
        "link_domain": "bankujesz.pl",
        "is_main_domain": true,
        "anchor": "Miejsce III TMS",
        "anchor_type": [],
        "count": {
          "count": 28,
          "percent_of_total": 0.004590916543695688
        },
        "domains_with_anchor_count": 1,
        "anchors_uniq_count": 28,
        "percent_of_total": 0.004590916543695688
      },
      {
        "link_domain": "bankujesz.pl",
        "is_main_domain": true,
        "anchor": "Miejsce II Admirals",
        "anchor_type": [],
        "count": {
          "count": 28,
          "percent_of_total": 0.004590916543695688
        },
        "domains_with_anchor_count": 1,
        "anchors_uniq_count": 28,
        "percent_of_total": 0.004590916543695688
      },
      {
        "link_domain": "bankujesz.pl",
        "is_main_domain": true,
        "anchor": "Ranking brokerów Forex styczeń 2024",
        "anchor_type": [],
        "count": {
          "count": 28,
          "percent_of_total": 0.004590916543695688
        },
        "domains_with_anchor_count": 1,
        "anchors_uniq_count": 28,
        "percent_of_total": 0.004590916543695688
      },
      {
        "link_domain": "bankujesz.pl",
        "is_main_domain": true,
        "anchor": "Ranking kantorów internetowych wrzesień",
        "anchor_type": [],
        "count": {
          "count": 27,
          "percent_of_total": 0.004426955238563699
        },
        "domains_with_anchor_count": 1,
        "anchors_uniq_count": 27,
        "percent_of_total": 0.004426955238563699
      },
      {
        "link_domain": "bankujesz.pl",
        "is_main_domain": true,
        "anchor": "oprocentowanie lokaty 3-miesięcznej",
        "anchor_type": [],
        "count": {
          "count": 25,
          "percent_of_total": 0.004099032628299721
        },
        "domains_with_anchor_count": 1,
        "anchors_uniq_count": 25,
        "percent_of_total": 0.004099032628299721
      },
      {
        "link_domain": "bankujesz.pl",
        "is_main_domain": true,
        "anchor": "Ranking kredytów konsolidacyjnych sierpień 2023",
        "anchor_type": [],
        "count": {
          "count": 22,
          "percent_of_total": 0.003607148712903755
        },
        "domains_with_anchor_count": 1,
        "anchors_uniq_count": 22,
        "percent_of_total": 0.003607148712903755
      },
      {
        "link_domain": "bankujesz.pl",
        "is_main_domain": true,
        "anchor": "kredytów dla firm",
        "anchor_type": [],
        "count": {
          "count": 22,
          "percent_of_total": 0.003607148712903755
        },
        "domains_with_anchor_count": 1,
        "anchors_uniq_count": 22,
        "percent_of_total": 0.003607148712903755
      },
      {
        "link_domain": "bankujesz.pl",
        "is_main_domain": true,
        "anchor": "Ranking kredytów gotówkowych na wrzesień 2023",
        "anchor_type": [],
        "count": {
          "count": 22,
          "percent_of_total": 0.003607148712903755
        },
        "domains_with_anchor_count": 1,
        "anchors_uniq_count": 21,
        "percent_of_total": 0.003607148712903755
      },
      {
        "link_domain": "bankujesz.pl",
        "is_main_domain": true,
        "anchor": "Ranking lokat bankowych",
        "anchor_type": [],
        "count": {
          "count": 22,
          "percent_of_total": 0.003607148712903755
        },
        "domains_with_anchor_count": 1,
        "anchors_uniq_count": 22,
        "percent_of_total": 0.003607148712903755
      },
      {
        "link_domain": "bankujesz.pl",
        "is_main_domain": true,
        "anchor": "Ranking kont forex",
        "anchor_type": [],
        "count": {
          "count": 19,
          "percent_of_total": 0.003115264797507788
        },
        "domains_with_anchor_count": 1,
        "anchors_uniq_count": 19,
        "percent_of_total": 0.003115264797507788
      },
      {
        "link_domain": "bankujesz.pl",
        "is_main_domain": true,
        "anchor": "wymianie walut",
        "anchor_type": [],
        "count": {
          "count": 16,
          "percent_of_total": 0.0026233808821118218
        },
        "domains_with_anchor_count": 1,
        "anchors_uniq_count": 15,
        "percent_of_total": 0.0026233808821118218
      },
      {
        "link_domain": "bankujesz.pl",
        "is_main_domain": true,
        "anchor": "Ranking kont oszczędnościowych",
        "anchor_type": [],
        "count": {
          "count": 16,
          "percent_of_total": 0.0026233808821118218
        },
        "domains_with_anchor_count": 1,
        "anchors_uniq_count": 16,
        "percent_of_total": 0.0026233808821118218
      },
      {
        "link_domain": "bankujesz.pl",
        "is_main_domain": true,
        "anchor": "Ranking lokat 6 miesięcznych sierpień 2023",
        "anchor_type": [],
        "count": {
          "count": 15,
          "percent_of_total": 0.002459419576979833
        },
        "domains_with_anchor_count": 1,
        "anchors_uniq_count": 14,
        "percent_of_total": 0.002459419576979833
      },
      {
        "link_domain": "bankujesz.pl",
        "is_main_domain": true,
        "anchor": "Ranking kart kredytowych sierpień",
        "anchor_type": [],
        "count": {
          "count": 14,
          "percent_of_total": 0.002295458271847844
        },
        "domains_with_anchor_count": 1,
        "anchors_uniq_count": 14,
        "percent_of_total": 0.002295458271847844
      },
      {
        "link_domain": "bankujesz.pl",
        "is_main_domain": true,
        "anchor": "Konta Walutowe",
        "anchor_type": [],
        "count": {
          "count": 14,
          "percent_of_total": 0.002295458271847844
        },
        "domains_with_anchor_count": 1,
        "anchors_uniq_count": 14,
        "percent_of_total": 0.002295458271847844
      },
      {
        "link_domain": "bankujesz.pl",
        "is_main_domain": true,
        "anchor": "Lokata 1 miesięczna Inbank",
        "anchor_type": [],
        "count": {
          "count": 13,
          "percent_of_total": 0.002131496966715855
        },
        "domains_with_anchor_count": 1,
        "anchors_uniq_count": 13,
        "percent_of_total": 0.002131496966715855
      },
      {
        "link_domain": "bankujesz.pl",
        "is_main_domain": true,
        "anchor": "Bankujesz",
        "anchor_type": [
          "multimedia"
        ],
        "count": {
          "count": 12,
          "percent_of_total": 0.001967535661583866
        },
        "domains_with_anchor_count": 2,
        "anchors_uniq_count": 4,
        "percent_of_total": 0.001967535661583866
      },
      {
        "link_domain": "bankujesz.pl",
        "is_main_domain": true,
        "anchor": "najlepsze konto osobiste",
        "anchor_type": [],
        "count": {
          "count": 12,
          "percent_of_total": 0.001967535661583866
        },
        "domains_with_anchor_count": 1,
        "anchors_uniq_count": 12,
        "percent_of_total": 0.001967535661583866
      },
      {
        "link_domain": "bankujesz.pl",
        "is_main_domain": true,
        "anchor": "Lokata 3 miesięczna",
        "anchor_type": [],
        "count": {
          "count": 12,
          "percent_of_total": 0.001967535661583866
        },
        "domains_with_anchor_count": 1,
        "anchors_uniq_count": 6,
        "percent_of_total": 0.001967535661583866
      },
      {
        "link_domain": "bankujesz.pl",
        "is_main_domain": true,
        "anchor": "12-miesięcznej lokaty",
        "anchor_type": [],
        "count": {
          "count": 12,
          "percent_of_total": 0.001967535661583866
        },
        "domains_with_anchor_count": 1,
        "anchors_uniq_count": 11,
        "percent_of_total": 0.001967535661583866
      },
      {
        "link_domain": "bankujesz.pl",
        "is_main_domain": true,
        "anchor": "Burza w Banku Światowym: Czy Jacek Kurski straci posadę?",
        "anchor_type": [],
        "count": {
          "count": 12,
          "percent_of_total": 0.001967535661583866
        },
        "domains_with_anchor_count": 1,
        "anchors_uniq_count": 12,
        "percent_of_total": 0.001967535661583866
      },
      {
        "link_domain": "bankujesz.pl",
        "is_main_domain": true,
        "anchor": "Miejsce 1 Lokata 3 miesięczna Velo Bank",
        "anchor_type": [],
        "count": {
          "count": 11,
          "percent_of_total": 0.0018035743564518774
        },
        "domains_with_anchor_count": 1,
        "anchors_uniq_count": 10,
        "percent_of_total": 0.0018035743564518774
      },
      {
        "link_domain": "bankujesz.pl",
        "is_main_domain": true,
        "anchor": "lokaty na 12 miesięcy",
        "anchor_type": [],
        "count": {
          "count": 11,
          "percent_of_total": 0.0018035743564518774
        },
        "domains_with_anchor_count": 1,
        "anchors_uniq_count": 10,
        "percent_of_total": 0.0018035743564518774
      },
      {
        "link_domain": "bankujesz.pl",
        "is_main_domain": true,
        "anchor": "bankujesz.pl",
        "anchor_type": [],
        "count": {
          "count": 11,
          "percent_of_total": 0.0018035743564518774
        },
        "domains_with_anchor_count": 1,
        "anchors_uniq_count": 11,
        "percent_of_total": 0.0018035743564518774
      },
      {
        "link_domain": "bankujesz.pl",
        "is_main_domain": true,
        "anchor": "Ranking lokat 3 miesięcznych grudzień 2023",
        "anchor_type": [],
        "count": {
          "count": 11,
          "percent_of_total": 0.0018035743564518774
        },
        "domains_with_anchor_count": 1,
        "anchors_uniq_count": 10,
        "percent_of_total": 0.0018035743564518774
      },
      {
        "link_domain": "bankujesz.pl",
        "is_main_domain": true,
        "anchor": "Miejsce 3 Lokata 3 miesięczna PKO BP",
        "anchor_type": [],
        "count": {
          "count": 11,
          "percent_of_total": 0.0018035743564518774
        },
        "domains_with_anchor_count": 1,
        "anchors_uniq_count": 10,
        "percent_of_total": 0.0018035743564518774
      },
      {
        "link_domain": "bankujesz.pl",
        "is_main_domain": true,
        "anchor": "wyboru kantoru internetowego",
        "anchor_type": [],
        "count": {
          "count": 11,
          "percent_of_total": 0.0018035743564518774
        },
        "domains_with_anchor_count": 1,
        "anchors_uniq_count": 11,
        "percent_of_total": 0.0018035743564518774
      },
      {
        "link_domain": "bankujesz.pl",
        "is_main_domain": true,
        "anchor": "Ranking kredytów konsolidacyjnych",
        "anchor_type": [],
        "count": {
          "count": 11,
          "percent_of_total": 0.0018035743564518774
        },
        "domains_with_anchor_count": 1,
        "anchors_uniq_count": 11,
        "percent_of_total": 0.0018035743564518774
      },
      {
        "link_domain": "bankujesz.pl",
        "is_main_domain": true,
        "anchor": "Miejsce 2 Lokata 3 miesięczna InBank",
        "anchor_type": [],
        "count": {
          "count": 11,
          "percent_of_total": 0.0018035743564518774
        },
        "domains_with_anchor_count": 1,
        "anchors_uniq_count": 10,
        "percent_of_total": 0.0018035743564518774
      },
      {
        "link_domain": "bankujesz.pl",
        "is_main_domain": true,
        "anchor": "Ranking kredytów hipotecznych",
        "anchor_type": [],
        "count": {
          "count": 11,
          "percent_of_total": 0.0018035743564518774
        },
        "domains_with_anchor_count": 1,
        "anchors_uniq_count": 11,
        "percent_of_total": 0.0018035743564518774
      },
      {
        "link_domain": "bankujesz.pl",
        "is_main_domain": true,
        "anchor": "lokaty 6-miesięczne",
        "anchor_type": [],
        "count": {
          "count": 11,
          "percent_of_total": 0.0018035743564518774
        },
        "domains_with_anchor_count": 1,
        "anchors_uniq_count": 11,
        "percent_of_total": 0.0018035743564518774
      },
      {
        "link_domain": "bankujesz.pl",
        "is_main_domain": true,
        "anchor": "Ranking kredytów hipotecznych wrzesień 2023",
        "anchor_type": [],
        "count": {
          "count": 10,
          "percent_of_total": 0.0016396130513198885
        },
        "domains_with_anchor_count": 1,
        "anchors_uniq_count": 10,
        "percent_of_total": 0.0016396130513198885
      },
      {
        "link_domain": "bankujesz.pl",
        "is_main_domain": true,
        "anchor": "Lokata 6 miesięczna Velo Bank",
        "anchor_type": [],
        "count": {
          "count": 10,
          "percent_of_total": 0.0016396130513198885
        },
        "domains_with_anchor_count": 1,
        "anchors_uniq_count": 10,
        "percent_of_total": 0.0016396130513198885
      },
      {
        "link_domain": "bankujesz.pl",
        "is_main_domain": true,
        "anchor": "Ranking 6-miesięcznych lokat bankowych grudzień 2023",
        "anchor_type": [],
        "count": {
          "count": 10,
          "percent_of_total": 0.0016396130513198885
        },
        "domains_with_anchor_count": 1,
        "anchors_uniq_count": 10,
        "percent_of_total": 0.0016396130513198885
      },
      {
        "link_domain": "bankujesz.pl",
        "is_main_domain": true,
        "anchor": "Bankujesz.pl?",
        "anchor_type": [],
        "count": {
          "count": 8,
          "percent_of_total": 0.0013116904410559109
        },
        "domains_with_anchor_count": 1,
        "anchors_uniq_count": 8,
        "percent_of_total": 0.0013116904410559109
      },
      {
        "link_domain": "bankujesz.pl",
        "is_main_domain": true,
        "anchor": "kantorów internetowych",
        "anchor_type": [],
        "count": {
          "count": 8,
          "percent_of_total": 0.0013116904410559109
        },
        "domains_with_anchor_count": 1,
        "anchors_uniq_count": 7,
        "percent_of_total": 0.0013116904410559109
      },
      {
        "link_domain": "bankujesz.pl",
        "is_main_domain": true,
        "anchor": "Bankujesz.pl",
        "anchor_type": [
          "multimedia"
        ],
        "count": {
          "count": 8,
          "percent_of_total": 0.0013116904410559109
        },
        "domains_with_anchor_count": 1,
        "anchors_uniq_count": 4,
        "percent_of_total": 0.0013116904410559109
      },
      {
        "link_domain": "bankujesz.pl",
        "is_main_domain": true,
        "anchor": "Ranking lokat 1 miesięcznych",
        "anchor_type": [],
        "count": {
          "count": 7,
          "percent_of_total": 0.001147729135923922
        },
        "domains_with_anchor_count": 1,
        "anchors_uniq_count": 7,
        "percent_of_total": 0.001147729135923922
      },
      {
        "link_domain": "bankujesz.pl",
        "is_main_domain": true,
        "anchor": "Lokaty 6 miesięczna",
        "anchor_type": [],
        "count": {
          "count": 7,
          "percent_of_total": 0.001147729135923922
        },
        "domains_with_anchor_count": 1,
        "anchors_uniq_count": 7,
        "percent_of_total": 0.001147729135923922
      },
      {
        "link_domain": "bankujesz.pl",
        "is_main_domain": true,
        "anchor": "Lokaty 12 miesięczna",
        "anchor_type": [],
        "count": {
          "count": 7,
          "percent_of_total": 0.001147729135923922
        },
        "domains_with_anchor_count": 1,
        "anchors_uniq_count": 7,
        "percent_of_total": 0.001147729135923922
      },
      {
        "link_domain": "bankujesz.pl",
        "is_main_domain": true,
        "anchor": "Ranking kantorów walutowych",
        "anchor_type": [],
        "count": {
          "count": 7,
          "percent_of_total": 0.001147729135923922
        },
        "domains_with_anchor_count": 1,
        "anchors_uniq_count": 6,
        "percent_of_total": 0.001147729135923922
      },
      {
        "link_domain": "bankujesz.pl",
        "is_main_domain": true,
        "anchor": "Ranking lokat 1 miesięcznych grudzień 2023",
        "anchor_type": [],
        "count": {
          "count": 7,
          "percent_of_total": 0.001147729135923922
        },
        "domains_with_anchor_count": 1,
        "anchors_uniq_count": 7,
        "percent_of_total": 0.001147729135923922
      },
      {
        "link_domain": "bankujesz.pl",
        "is_main_domain": true,
        "anchor": "Lokata 1 miesięczna Santander",
        "anchor_type": [],
        "count": {
          "count": 7,
          "percent_of_total": 0.001147729135923922
        },
        "domains_with_anchor_count": 1,
        "anchors_uniq_count": 7,
        "percent_of_total": 0.001147729135923922
      },
      {
        "link_domain": "bankujesz.pl",
        "is_main_domain": true,
        "anchor": "Lokata 3-miesięczna",
        "anchor_type": [],
        "count": {
          "count": 7,
          "percent_of_total": 0.001147729135923922
        },
        "domains_with_anchor_count": 1,
        "anchors_uniq_count": 7,
        "percent_of_total": 0.001147729135923922
      },
      {
        "link_domain": "bankujesz.pl",
        "is_main_domain": true,
        "anchor": "kantory internetowe online",
        "anchor_type": [],
        "count": {
          "count": 7,
          "percent_of_total": 0.001147729135923922
        },
        "domains_with_anchor_count": 1,
        "anchors_uniq_count": 6,
        "percent_of_total": 0.001147729135923922
      },
      {
        "link_domain": "bankujesz.pl",
        "is_main_domain": true,
        "anchor": "Lokata 1 miesięczna Velo Bank",
        "anchor_type": [],
        "count": {
          "count": 7,
          "percent_of_total": 0.001147729135923922
        },
        "domains_with_anchor_count": 1,
        "anchors_uniq_count": 7,
        "percent_of_total": 0.001147729135923922
      },
      {
        "link_domain": "bankujesz.pl",
        "is_main_domain": true,
        "anchor": "PKO BP",
        "anchor_type": [],
        "count": {
          "count": 6,
          "percent_of_total": 0.000983767830791933
        },
        "domains_with_anchor_count": 1,
        "anchors_uniq_count": 4,
        "percent_of_total": 0.000983767830791933
      },
      {
        "link_domain": "bankujesz.pl",
        "is_main_domain": true,
        "anchor": "Lokata 1 miesięczna Santander Bank",
        "anchor_type": [],
        "count": {
          "count": 6,
          "percent_of_total": 0.000983767830791933
        },
        "domains_with_anchor_count": 1,
        "anchors_uniq_count": 6,
        "percent_of_total": 0.000983767830791933
      },
      {
        "link_domain": "bankujesz.pl",
        "is_main_domain": true,
        "anchor": "ranking lokat 1 miesięcznych listopad 2023",
        "anchor_type": [],
        "count": {
          "count": 6,
          "percent_of_total": 0.000983767830791933
        },
        "domains_with_anchor_count": 1,
        "anchors_uniq_count": 6,
        "percent_of_total": 0.000983767830791933
      },
      {
        "link_domain": "bankujesz.pl",
        "is_main_domain": true,
        "anchor": "aktualny ranknig kont oszczędnościowych",
        "anchor_type": [],
        "count": {
          "count": 6,
          "percent_of_total": 0.000983767830791933
        },
        "domains_with_anchor_count": 1,
        "anchors_uniq_count": 6,
        "percent_of_total": 0.000983767830791933
      },
      {
        "link_domain": "bankujesz.pl",
        "is_main_domain": true,
        "anchor": "Ranking kont maklerskich wrzesień 2023",
        "anchor_type": [],
        "count": {
          "count": 6,
          "percent_of_total": 0.000983767830791933
        },
        "domains_with_anchor_count": 1,
        "anchors_uniq_count": 6,
        "percent_of_total": 0.000983767830791933
      },
      {
        "link_domain": "bankujesz.pl",
        "is_main_domain": true,
        "anchor": "bankujesz.pl.",
        "anchor_type": [],
        "count": {
          "count": 6,
          "percent_of_total": 0.000983767830791933
        },
        "domains_with_anchor_count": 1,
        "anchors_uniq_count": 6,
        "percent_of_total": 0.000983767830791933
      },
      {
        "link_domain": "bankujesz.pl",
        "is_main_domain": true,
        "anchor": "Lokata 3 miesięczna InBank",
        "anchor_type": [],
        "count": {
          "count": 6,
          "percent_of_total": 0.000983767830791933
        },
        "domains_with_anchor_count": 1,
        "anchors_uniq_count": 6,
        "percent_of_total": 0.000983767830791933
      },
      {
        "link_domain": "bankujesz.pl",
        "is_main_domain": true,
        "anchor": "Kantor",
        "anchor_type": [],
        "count": {
          "count": 5,
          "percent_of_total": 0.0008198065256599442
        },
        "domains_with_anchor_count": 1,
        "anchors_uniq_count": 5,
        "percent_of_total": 0.0008198065256599442
      },
      {
        "link_domain": "bankujesz.pl",
        "is_main_domain": true,
        "anchor": "Kantor internetowy",
        "anchor_type": [],
        "count": {
          "count": 5,
          "percent_of_total": 0.0008198065256599442
        },
        "domains_with_anchor_count": 1,
        "anchors_uniq_count": 5,
        "percent_of_total": 0.0008198065256599442
      },
      {
        "link_domain": "bankujesz.pl",
        "is_main_domain": true,
        "anchor": "oferty kont Forex",
        "anchor_type": [],
        "count": {
          "count": 5,
          "percent_of_total": 0.0008198065256599442
        },
        "domains_with_anchor_count": 1,
        "anchors_uniq_count": 5,
        "percent_of_total": 0.0008198065256599442
      },
      {
        "link_domain": "bankujesz.pl",
        "is_main_domain": true,
        "anchor": "Szczegoły",
        "anchor_type": [],
        "count": {
          "count": 5,
          "percent_of_total": 0.0008198065256599442
        },
        "domains_with_anchor_count": 1,
        "anchors_uniq_count": 1,
        "percent_of_total": 0.0008198065256599442
      },
      {
        "link_domain": "bankujesz.pl",
        "is_main_domain": true,
        "anchor": "Kurs Pekao SA we czwartek, 12 października. Ile kosztują dziś akcje Pekao?",
        "anchor_type": [],
        "count": {
          "count": 4,
          "percent_of_total": 0.0006558452205279554
        },
        "domains_with_anchor_count": 1,
        "anchors_uniq_count": 3,
        "percent_of_total": 0.0006558452205279554
      },
      {
        "link_domain": "bankujesz.pl",
        "is_main_domain": true,
        "anchor": "Ranking lokat 3 miesięcznych sierpień 2023",
        "anchor_type": [],
        "count": {
          "count": 4,
          "percent_of_total": 0.0006558452205279554
        },
        "domains_with_anchor_count": 1,
        "anchors_uniq_count": 4,
        "percent_of_total": 0.0006558452205279554
      },
      {
        "link_domain": "bankujesz.pl",
        "is_main_domain": true,
        "anchor": "Szczegóły oferty",
        "anchor_type": [],
        "count": {
          "count": 4,
          "percent_of_total": 0.0006558452205279554
        },
        "domains_with_anchor_count": 1,
        "anchors_uniq_count": 1,
        "percent_of_total": 0.0006558452205279554
      },
      {
        "link_domain": "bankujesz.pl",
        "is_main_domain": true,
        "anchor": "kredytów konsolidacyjnych na listopad 2023",
        "anchor_type": [],
        "count": {
          "count": 3,
          "percent_of_total": 0.0004918839153959665
        },
        "domains_with_anchor_count": 1,
        "anchors_uniq_count": 3,
        "percent_of_total": 0.0004918839153959665
      },
      {
        "link_domain": "bankujesz.pl",
        "is_main_domain": true,
        "anchor": "Ranking kont dla młodych wrzesień 2023",
        "anchor_type": [],
        "count": {
          "count": 3,
          "percent_of_total": 0.0004918839153959665
        },
        "domains_with_anchor_count": 1,
        "anchors_uniq_count": 3,
        "percent_of_total": 0.0004918839153959665
      },
      {
        "link_domain": "bankujesz.pl",
        "is_main_domain": true,
        "anchor": "Szczegóły",
        "anchor_type": [],
        "count": {
          "count": 3,
          "percent_of_total": 0.0004918839153959665
        },
        "domains_with_anchor_count": 1,
        "anchors_uniq_count": 3,
        "percent_of_total": 0.0004918839153959665
      },
      {
        "link_domain": "bankujesz.pl",
        "is_main_domain": true,
        "anchor": "Dowiedz się więcej",
        "anchor_type": [],
        "count": {
          "count": 3,
          "percent_of_total": 0.0004918839153959665
        },
        "domains_with_anchor_count": 1,
        "anchors_uniq_count": 1,
        "percent_of_total": 0.0004918839153959665
      },
      {
        "link_domain": "bankujesz.pl",
        "is_main_domain": true,
        "anchor": "Ranking lokat 1 miesięcznych sierpień 2023",
        "anchor_type": [],
        "count": {
          "count": 3,
          "percent_of_total": 0.0004918839153959665
        },
        "domains_with_anchor_count": 1,
        "anchors_uniq_count": 2,
        "percent_of_total": 0.0004918839153959665
      },
      {
        "link_domain": "bankujesz.pl",
        "is_main_domain": true,
        "anchor": "Kredyt konsolidacyjny Pekao SA",
        "anchor_type": [],
        "count": {
          "count": 3,
          "percent_of_total": 0.0004918839153959665
        },
        "domains_with_anchor_count": 1,
        "anchors_uniq_count": 3,
        "percent_of_total": 0.0004918839153959665
      },
      {
        "link_domain": "bankujesz.pl",
        "is_main_domain": true,
        "anchor": "Pekao",
        "anchor_type": [],
        "count": {
          "count": 3,
          "percent_of_total": 0.0004918839153959665
        },
        "domains_with_anchor_count": 1,
        "anchors_uniq_count": 3,
        "percent_of_total": 0.0004918839153959665
      },
      {
        "link_domain": "bankujesz.pl",
        "is_main_domain": true,
        "anchor": "Banku BNP Pariba",
        "anchor_type": [],
        "count": {
          "count": 3,
          "percent_of_total": 0.0004918839153959665
        },
        "domains_with_anchor_count": 1,
        "anchors_uniq_count": 1,
        "percent_of_total": 0.0004918839153959665
      },
      {
        "link_domain": "bankujesz.pl",
        "is_main_domain": true,
        "anchor": "bankujesz.pl logo",
        "anchor_type": [
          "multimedia"
        ],
        "count": {
          "count": 3,
          "percent_of_total": 0.0004918839153959665
        },
        "domains_with_anchor_count": 1,
        "anchors_uniq_count": 2,
        "percent_of_total": 0.0004918839153959665
      },
      {
        "link_domain": "bankujesz.pl",
        "is_main_domain": true,
        "anchor": "Kredyt konsolidacyjny Alior Bank",
        "anchor_type": [],
        "count": {
          "count": 3,
          "percent_of_total": 0.0004918839153959665
        },
        "domains_with_anchor_count": 1,
        "anchors_uniq_count": 3,
        "percent_of_total": 0.0004918839153959665
      },
      {
        "link_domain": "bankujesz.pl",
        "is_main_domain": true,
        "anchor": "Kredyt konsolidacyjny Kasa Stefczyka",
        "anchor_type": [],
        "count": {
          "count": 3,
          "percent_of_total": 0.0004918839153959665
        },
        "domains_with_anchor_count": 1,
        "anchors_uniq_count": 3,
        "percent_of_total": 0.0004918839153959665
      },
      {
        "link_domain": "bankujesz.pl",
        "is_main_domain": true,
        "anchor": "Lokaty bankowe 6 miesięczne",
        "anchor_type": [],
        "count": {
          "count": 2,
          "percent_of_total": 0.0003279226102639777
        },
        "domains_with_anchor_count": 1,
        "anchors_uniq_count": 2,
        "percent_of_total": 0.0003279226102639777
      },
      {
        "link_domain": "bankujesz.pl",
        "is_main_domain": true,
        "anchor": "Miejsce 2 Karta kredytowa Credit Agricole",
        "anchor_type": [],
        "count": {
          "count": 2,
          "percent_of_total": 0.0003279226102639777
        },
        "domains_with_anchor_count": 1,
        "anchors_uniq_count": 2,
        "percent_of_total": 0.0003279226102639777
      },
      {
        "link_domain": "bankujesz.pl",
        "is_main_domain": true,
        "anchor": "Ranking kart kredytowych listopad 2023",
        "anchor_type": [],
        "count": {
          "count": 2,
          "percent_of_total": 0.0003279226102639777
        },
        "domains_with_anchor_count": 1,
        "anchors_uniq_count": 2,
        "percent_of_total": 0.0003279226102639777
      },
      {
        "link_domain": "bankujesz.pl",
        "is_main_domain": true,
        "anchor": "Miejsce 1 Karta kredytowa Pekao SA",
        "anchor_type": [],
        "count": {
          "count": 2,
          "percent_of_total": 0.0003279226102639777
        },
        "domains_with_anchor_count": 1,
        "anchors_uniq_count": 2,
        "percent_of_total": 0.0003279226102639777
      },
      {
        "link_domain": "bankujesz.pl",
        "is_main_domain": true,
        "anchor": "Lokaty bankowe 12 miesięczne",
        "anchor_type": [],
        "count": {
          "count": 2,
          "percent_of_total": 0.0003279226102639777
        },
        "domains_with_anchor_count": 1,
        "anchors_uniq_count": 2,
        "percent_of_total": 0.0003279226102639777
      },
      {
        "link_domain": "bankujesz.pl",
        "is_main_domain": true,
        "anchor": "Ranking lokat 1 miesięcznych lipiec",
        "anchor_type": [],
        "count": {
          "count": 2,
          "percent_of_total": 0.0003279226102639777
        },
        "domains_with_anchor_count": 1,
        "anchors_uniq_count": 2,
        "percent_of_total": 0.0003279226102639777
      },
      {
        "link_domain": "bankujesz.pl",
        "is_main_domain": true,
        "anchor": "https://www.bankujesz.pl/",
        "anchor_type": [
          "naked"
        ],
        "count": {
          "count": 2,
          "percent_of_total": 0.0003279226102639777
        },
        "domains_with_anchor_count": 1,
        "anchors_uniq_count": 2,
        "percent_of_total": 0.0003279226102639777
      },
      {
        "link_domain": "bankujesz.pl",
        "is_main_domain": true,
        "anchor": "kredytu hipotecznego",
        "anchor_type": [],
        "count": {
          "count": 2,
          "percent_of_total": 0.0003279226102639777
        },
        "domains_with_anchor_count": 1,
        "anchors_uniq_count": 2,
        "percent_of_total": 0.0003279226102639777
      },
      {
        "link_domain": "bankujesz.pl",
        "is_main_domain": true,
        "anchor": "Ranking kredytów firmowych listopad 2023",
        "anchor_type": [],
        "count": {
          "count": 2,
          "percent_of_total": 0.0003279226102639777
        },
        "domains_with_anchor_count": 1,
        "anchors_uniq_count": 2,
        "percent_of_total": 0.0003279226102639777
      },
      {
        "link_domain": "bankujesz.pl",
        "is_main_domain": true,
        "anchor": "Bankujesz.pl",
        "anchor_type": [],
        "count": {
          "count": 2,
          "percent_of_total": 0.0003279226102639777
        },
        "domains_with_anchor_count": 1,
        "anchors_uniq_count": 2,
        "percent_of_total": 0.0003279226102639777
      },
      {
        "link_domain": "bankujesz.pl",
        "is_main_domain": true,
        "anchor": "konto oszczędnościowe",
        "anchor_type": [],
        "count": {
          "count": 2,
          "percent_of_total": 0.0003279226102639777
        },
        "domains_with_anchor_count": 1,
        "anchors_uniq_count": 2,
        "percent_of_total": 0.0003279226102639777
      },
      {
        "link_domain": "bankujesz.pl",
        "is_main_domain": true,
        "anchor": "Miejsce 3 Karta kredytowa Santander",
        "anchor_type": [],
        "count": {
          "count": 2,
          "percent_of_total": 0.0003279226102639777
        },
        "domains_with_anchor_count": 1,
        "anchors_uniq_count": 2,
        "percent_of_total": 0.0003279226102639777
      },
      {
        "link_domain": "bankujesz.pl",
        "is_main_domain": true,
        "anchor": "Lokaty bankowe 3 miesięczne",
        "anchor_type": [],
        "count": {
          "count": 2,
          "percent_of_total": 0.0003279226102639777
        },
        "domains_with_anchor_count": 1,
        "anchors_uniq_count": 2,
        "percent_of_total": 0.0003279226102639777
      },
      {
        "link_domain": "bankujesz.pl",
        "is_main_domain": true,
        "anchor": "Kantor Internetowy InternetowyKantor.pl",
        "anchor_type": [],
        "count": {
          "count": 1,
          "percent_of_total": 0.00016396130513198886
        },
        "domains_with_anchor_count": 1,
        "anchors_uniq_count": 1,
        "percent_of_total": 0.00016396130513198886
      },
      {
        "link_domain": "bankujesz.pl",
        "is_main_domain": true,
        "anchor": "Bank Pekao karta kredytowa wrzesień 2023",
        "anchor_type": [],
        "count": {
          "count": 1,
          "percent_of_total": 0.00016396130513198886
        },
        "domains_with_anchor_count": 1,
        "anchors_uniq_count": 1,
        "percent_of_total": 0.00016396130513198886
      },
      {
        "link_domain": "bankujesz.pl",
        "is_main_domain": true,
        "anchor": "Kantor internetowy Cinkciarz",
        "anchor_type": [],
        "count": {
          "count": 1,
          "percent_of_total": 0.00016396130513198886
        },
        "domains_with_anchor_count": 1,
        "anchors_uniq_count": 1,
        "percent_of_total": 0.00016396130513198886
      },
      {
        "link_domain": "bankujesz.pl",
        "is_main_domain": true,
        "anchor": "Giełda Kryptowalut Zonda",
        "anchor_type": [],
        "count": {
          "count": 1,
          "percent_of_total": 0.00016396130513198886
        },
        "domains_with_anchor_count": 1,
        "anchors_uniq_count": 1,
        "percent_of_total": 0.00016396130513198886
      },
      {
        "link_domain": "bankujesz.pl",
        "is_main_domain": true,
        "anchor": "bankujesz.pl (Polish only)",
        "anchor_type": [],
        "count": {
          "count": 1,
          "percent_of_total": 0.00016396130513198886
        },
        "domains_with_anchor_count": 1,
        "anchors_uniq_count": 1,
        "percent_of_total": 0.00016396130513198886
      },
      {
        "link_domain": "bankujesz.pl",
        "is_main_domain": true,
        "anchor": "Miejsce II Zonda",
        "anchor_type": [],
        "count": {
          "count": 1,
          "percent_of_total": 0.00016396130513198886
        },
        "domains_with_anchor_count": 1,
        "anchors_uniq_count": 1,
        "percent_of_total": 0.00016396130513198886
      },
      {
        "link_domain": "bankujesz.pl",
        "is_main_domain": true,
        "anchor": "Alior Bank.",
        "anchor_type": [],
        "count": {
          "count": 1,
          "percent_of_total": 0.00016396130513198886
        },
        "domains_with_anchor_count": 1,
        "anchors_uniq_count": 1,
        "percent_of_total": 0.00016396130513198886
      },
      {
        "link_domain": "bankujesz.pl",
        "is_main_domain": true,
        "anchor": "Konto osobiste BNP Paribas",
        "anchor_type": [],
        "count": {
          "count": 1,
          "percent_of_total": 0.00016396130513198886
        },
        "domains_with_anchor_count": 1,
        "anchors_uniq_count": 1,
        "percent_of_total": 0.00016396130513198886
      },
      {
        "link_domain": "bankujesz.pl",
        "is_main_domain": true,
        "anchor": "Konto Walutowe PKO BP",
        "anchor_type": [],
        "count": {
          "count": 1,
          "percent_of_total": 0.00016396130513198886
        },
        "domains_with_anchor_count": 1,
        "anchors_uniq_count": 1,
        "percent_of_total": 0.00016396130513198886
      },
      {
        "link_domain": "bankujesz.pl",
        "is_main_domain": true,
        "anchor": "Ranking konto ososbistych grodzień 2023",
        "anchor_type": [],
        "count": {
          "count": 1,
          "percent_of_total": 0.00016396130513198886
        },
        "domains_with_anchor_count": 1,
        "anchors_uniq_count": 1,
        "percent_of_total": 0.00016396130513198886
      },
      {
        "link_domain": "bankujesz.pl",
        "is_main_domain": true,
        "anchor": "Miejsce 3 Lokata 3 miesięczna Bank Nowy",
        "anchor_type": [],
        "count": {
          "count": 1,
          "percent_of_total": 0.00016396130513198886
        },
        "domains_with_anchor_count": 1,
        "anchors_uniq_count": 1,
        "percent_of_total": 0.00016396130513198886
      },
      {
        "link_domain": "bankujesz.pl",
        "is_main_domain": true,
        "anchor": "oferta rachunków oszczędnościowych",
        "anchor_type": [],
        "count": {
          "count": 1,
          "percent_of_total": 0.00016396130513198886
        },
        "domains_with_anchor_count": 1,
        "anchors_uniq_count": 1,
        "percent_of_total": 0.00016396130513198886
      },
      {
        "link_domain": "bankujesz.pl",
        "is_main_domain": true,
        "anchor": "Ranking lokat 3-miesięcznych",
        "anchor_type": [],
        "count": {
          "count": 1,
          "percent_of_total": 0.00016396130513198886
        },
        "domains_with_anchor_count": 1,
        "anchors_uniq_count": 1,
        "percent_of_total": 0.00016396130513198886
      },
      {
        "link_domain": "bankujesz.pl",
        "is_main_domain": true,
        "anchor": "Miejsce I Binance",
        "anchor_type": [],
        "count": {
          "count": 1,
          "percent_of_total": 0.00016396130513198886
        },
        "domains_with_anchor_count": 1,
        "anchors_uniq_count": 1,
        "percent_of_total": 0.00016396130513198886
      },
      {
        "link_domain": "bankujesz.pl",
        "is_main_domain": true,
        "anchor": "Ranking giełd kryptowalut grudzień 2023",
        "anchor_type": [],
        "count": {
          "count": 1,
          "percent_of_total": 0.00016396130513198886
        },
        "domains_with_anchor_count": 1,
        "anchors_uniq_count": 1,
        "percent_of_total": 0.00016396130513198886
      },
      {
        "link_domain": "bankujesz.pl",
        "is_main_domain": true,
        "anchor": "Kredyt hipoteczny Pekao SA",
        "anchor_type": [],
        "count": {
          "count": 1,
          "percent_of_total": 0.00016396130513198886
        },
        "domains_with_anchor_count": 1,
        "anchors_uniq_count": 1,
        "percent_of_total": 0.00016396130513198886
      },
      {
        "link_domain": "bankujesz.pl",
        "is_main_domain": true,
        "anchor": "Miejsce III Egera",
        "anchor_type": [],
        "count": {
          "count": 1,
          "percent_of_total": 0.00016396130513198886
        },
        "domains_with_anchor_count": 1,
        "anchors_uniq_count": 1,
        "percent_of_total": 0.00016396130513198886
      },
      {
        "link_domain": "bankujesz.pl",
        "is_main_domain": true,
        "anchor": "Kredyt gotówkowy BNP Paribas",
        "anchor_type": [],
        "count": {
          "count": 1,
          "percent_of_total": 0.00016396130513198886
        },
        "domains_with_anchor_count": 1,
        "anchors_uniq_count": 1,
        "percent_of_total": 0.00016396130513198886
      },
      {
        "link_domain": "bankujesz.pl",
        "is_main_domain": true,
        "anchor": "Miejsce 2 Lokata 3 miesięczna Velo Bank",
        "anchor_type": [],
        "count": {
          "count": 1,
          "percent_of_total": 0.00016396130513198886
        },
        "domains_with_anchor_count": 1,
        "anchors_uniq_count": 1,
        "percent_of_total": 0.00016396130513198886
      },
      {
        "link_domain": "bankujesz.pl",
        "is_main_domain": true,
        "anchor": "Kredyt gotówkowy Millennium",
        "anchor_type": [],
        "count": {
          "count": 1,
          "percent_of_total": 0.00016396130513198886
        },
        "domains_with_anchor_count": 1,
        "anchors_uniq_count": 1,
        "percent_of_total": 0.00016396130513198886
      },
      {
        "link_domain": "bankujesz.pl",
        "is_main_domain": true,
        "anchor": "mBank",
        "anchor_type": [],
        "count": {
          "count": 1,
          "percent_of_total": 0.00016396130513198886
        },
        "domains_with_anchor_count": 1,
        "anchors_uniq_count": 1,
        "percent_of_total": 0.00016396130513198886
      },
      {
        "link_domain": "bankujesz.pl",
        "is_main_domain": true,
        "anchor": "Kantor Internetowy Alior Bank",
        "anchor_type": [],
        "count": {
          "count": 1,
          "percent_of_total": 0.00016396130513198886
        },
        "domains_with_anchor_count": 1,
        "anchors_uniq_count": 1,
        "percent_of_total": 0.00016396130513198886
      },
      {
        "link_domain": "bankujesz.pl",
        "is_main_domain": true,
        "anchor": "Czym jest rachunek dla dziecka?",
        "anchor_type": [],
        "count": {
          "count": 1,
          "percent_of_total": 0.00016396130513198886
        },
        "domains_with_anchor_count": 1,
        "anchors_uniq_count": 1,
        "percent_of_total": 0.00016396130513198886
      },
      {
        "link_domain": "bankujesz.pl",
        "is_main_domain": true,
        "anchor": "Miejsce 2 Konto Oszczędnościowe Nest Bank",
        "anchor_type": [],
        "count": {
          "count": 1,
          "percent_of_total": 0.00016396130513198886
        },
        "domains_with_anchor_count": 1,
        "anchors_uniq_count": 1,
        "percent_of_total": 0.00016396130513198886
      },
      {
        "link_domain": "bankujesz.pl",
        "is_main_domain": true,
        "anchor": "Konto osobiste Millennium",
        "anchor_type": [],
        "count": {
          "count": 1,
          "percent_of_total": 0.00016396130513198886
        },
        "domains_with_anchor_count": 1,
        "anchors_uniq_count": 1,
        "percent_of_total": 0.00016396130513198886
      },
      {
        "link_domain": "bankujesz.pl",
        "is_main_domain": true,
        "anchor": "lokaty 3 miesięczne",
        "anchor_type": [],
        "count": {
          "count": 1,
          "percent_of_total": 0.00016396130513198886
        },
        "domains_with_anchor_count": 1,
        "anchors_uniq_count": 1,
        "percent_of_total": 0.00016396130513198886
      },
      {
        "link_domain": "bankujesz.pl",
        "is_main_domain": true,
        "anchor": "Kredyt gotówkowy Credit Agricole",
        "anchor_type": [],
        "count": {
          "count": 1,
          "percent_of_total": 0.00016396130513198886
        },
        "domains_with_anchor_count": 1,
        "anchors_uniq_count": 1,
        "percent_of_total": 0.00016396130513198886
      },
      {
        "link_domain": "bankujesz.pl",
        "is_main_domain": true,
        "anchor": "Pekao SA",
        "anchor_type": [],
        "count": {
          "count": 1,
          "percent_of_total": 0.00016396130513198886
        },
        "domains_with_anchor_count": 1,
        "anchors_uniq_count": 1,
        "percent_of_total": 0.00016396130513198886
      },
      {
        "link_domain": "bankujesz.pl",
        "is_main_domain": true,
        "anchor": "Konto Walutowe Alior Bank",
        "anchor_type": [],
        "count": {
          "count": 1,
          "percent_of_total": 0.00016396130513198886
        },
        "domains_with_anchor_count": 1,
        "anchors_uniq_count": 1,
        "percent_of_total": 0.00016396130513198886
      },
      {
        "link_domain": "bankujesz.pl",
        "is_main_domain": true,
        "anchor": "Miejsce I Binance",
        "anchor_type": [],
        "count": {
          "count": 1,
          "percent_of_total": 0.00016396130513198886
        },
        "domains_with_anchor_count": 1,
        "anchors_uniq_count": 1,
        "percent_of_total": 0.00016396130513198886
      },
      {
        "link_domain": "bankujesz.pl",
        "is_main_domain": true,
        "anchor": "Ranking giełd kryptowalut styczeń 2024",
        "anchor_type": [],
        "count": {
          "count": 1,
          "percent_of_total": 0.00016396130513198886
        },
        "domains_with_anchor_count": 1,
        "anchors_uniq_count": 1,
        "percent_of_total": 0.00016396130513198886
      },
      {
        "link_domain": "bankujesz.pl",
        "is_main_domain": true,
        "anchor": "notowania Santader",
        "anchor_type": [],
        "count": {
          "count": 1,
          "percent_of_total": 0.00016396130513198886
        },
        "domains_with_anchor_count": 1,
        "anchors_uniq_count": 1,
        "percent_of_total": 0.00016396130513198886
      },
      {
        "link_domain": "bankujesz.pl",
        "is_main_domain": true,
        "anchor": "edyt gotówkowy Kasa Stefczyka",
        "anchor_type": [],
        "count": {
          "count": 1,
          "percent_of_total": 0.00016396130513198886
        },
        "domains_with_anchor_count": 1,
        "anchors_uniq_count": 1,
        "percent_of_total": 0.00016396130513198886
      },
      {
        "link_domain": "bankujesz.pl",
        "is_main_domain": true,
        "anchor": "Kantor Internetowy InternetowyKantor.pl",
        "anchor_type": [],
        "count": {
          "count": 1,
          "percent_of_total": 0.00016396130513198886
        },
        "domains_with_anchor_count": 1,
        "anchors_uniq_count": 1,
        "percent_of_total": 0.00016396130513198886
      },
      {
        "link_domain": "bankujesz.pl",
        "is_main_domain": true,
        "anchor": "Ranking konto ososbistych grodzień 2023",
        "anchor_type": [],
        "count": {
          "count": 1,
          "percent_of_total": 0.00016396130513198886
        },
        "domains_with_anchor_count": 1,
        "anchors_uniq_count": 1,
        "percent_of_total": 0.00016396130513198886
      },
      {
        "link_domain": "bankujesz.pl",
        "is_main_domain": true,
        "anchor": "Miejsce II Zonda",
        "anchor_type": [],
        "count": {
          "count": 1,
          "percent_of_total": 0.00016396130513198886
        },
        "domains_with_anchor_count": 1,
        "anchors_uniq_count": 1,
        "percent_of_total": 0.00016396130513198886
      },
      {
        "link_domain": "bankujesz.pl",
        "is_main_domain": true,
        "anchor": "Konto osobiste BNP Paribas",
        "anchor_type": [],
        "count": {
          "count": 1,
          "percent_of_total": 0.00016396130513198886
        },
        "domains_with_anchor_count": 1,
        "anchors_uniq_count": 1,
        "percent_of_total": 0.00016396130513198886
      },
      {
        "link_domain": "bankujesz.pl",
        "is_main_domain": true,
        "anchor": "Kantor internetowy Cinkciarz",
        "anchor_type": [],
        "count": {
          "count": 1,
          "percent_of_total": 0.00016396130513198886
        },
        "domains_with_anchor_count": 1,
        "anchors_uniq_count": 1,
        "percent_of_total": 0.00016396130513198886
      },
      {
        "link_domain": "bankujesz.pl",
        "is_main_domain": true,
        "anchor": "Bank Pekao karta kredytowa wrzesień 2023",
        "anchor_type": [],
        "count": {
          "count": 1,
          "percent_of_total": 0.00016396130513198886
        },
        "domains_with_anchor_count": 1,
        "anchors_uniq_count": 1,
        "percent_of_total": 0.00016396130513198886
      },
      {
        "link_domain": "bankujesz.pl",
        "is_main_domain": true,
        "anchor": "kurs akcji mBank",
        "anchor_type": [],
        "count": {
          "count": 1,
          "percent_of_total": 0.00016396130513198886
        },
        "domains_with_anchor_count": 1,
        "anchors_uniq_count": 1,
        "percent_of_total": 0.00016396130513198886
      },
      {
        "link_domain": "bankujesz.pl",
        "is_main_domain": true,
        "anchor": "Kredyt hipoteczny w Citi Handlowym",
        "anchor_type": [],
        "count": {
          "count": 1,
          "percent_of_total": 0.00016396130513198886
        },
        "domains_with_anchor_count": 1,
        "anchors_uniq_count": 1,
        "percent_of_total": 0.00016396130513198886
      },
      {
        "link_domain": "bankujesz.pl",
        "is_main_domain": true,
        "anchor": "lokaty terminowej na 12 miesięcy",
        "anchor_type": [],
        "count": {
          "count": 1,
          "percent_of_total": 0.00016396130513198886
        },
        "domains_with_anchor_count": 1,
        "anchors_uniq_count": 1,
        "percent_of_total": 0.00016396130513198886
      },
      {
        "link_domain": "bankujesz.pl",
        "is_main_domain": true,
        "anchor": "Ranking kont oszczędnościowych styczeń 2024",
        "anchor_type": [],
        "count": {
          "count": 1,
          "percent_of_total": 0.00016396130513198886
        },
        "domains_with_anchor_count": 1,
        "anchors_uniq_count": 1,
        "percent_of_total": 0.00016396130513198886
      },
      {
        "link_domain": "bankujesz.pl",
        "is_main_domain": true,
        "anchor": "oferta rachunków oszczędnościowych",
        "anchor_type": [],
        "count": {
          "count": 1,
          "percent_of_total": 0.00016396130513198886
        },
        "domains_with_anchor_count": 1,
        "anchors_uniq_count": 1,
        "percent_of_total": 0.00016396130513198886
      },
      {
        "link_domain": "bankujesz.pl",
        "is_main_domain": true,
        "anchor": "Kredyt gotówkowy Credit Agricole",
        "anchor_type": [],
        "count": {
          "count": 1,
          "percent_of_total": 0.00016396130513198886
        },
        "domains_with_anchor_count": 1,
        "anchors_uniq_count": 1,
        "percent_of_total": 0.00016396130513198886
      },
      {
        "link_domain": "bankujesz.pl",
        "is_main_domain": true,
        "anchor": "Poczta Polska w kryzysie. Bezpieczeństwo finansowe wisi na włosku, pracownicy strajkują. Czy jest nadzieja na przetrwanie?",
        "anchor_type": [],
        "count": {
          "count": 1,
          "percent_of_total": 0.00016396130513198886
        },
        "domains_with_anchor_count": 1,
        "anchors_uniq_count": 1,
        "percent_of_total": 0.00016396130513198886
      },
      {
        "link_domain": "bankujesz.pl",
        "is_main_domain": true,
        "anchor": "Konto osobiste Millennium",
        "anchor_type": [],
        "count": {
          "count": 1,
          "percent_of_total": 0.00016396130513198886
        },
        "domains_with_anchor_count": 1,
        "anchors_uniq_count": 1,
        "percent_of_total": 0.00016396130513198886
      },
      {
        "link_domain": "bankujesz.pl",
        "is_main_domain": true,
        "anchor": "Kantor internetowy Walutomat",
        "anchor_type": [],
        "count": {
          "count": 1,
          "percent_of_total": 0.00016396130513198886
        },
        "domains_with_anchor_count": 1,
        "anchors_uniq_count": 1,
        "percent_of_total": 0.00016396130513198886
      },
      {
        "link_domain": "bankujesz.pl",
        "is_main_domain": true,
        "anchor": "Kredyt firmowy w Alior Banku",
        "anchor_type": [],
        "count": {
          "count": 1,
          "percent_of_total": 0.00016396130513198886
        },
        "domains_with_anchor_count": 1,
        "anchors_uniq_count": 1,
        "percent_of_total": 0.00016396130513198886
      },
      {
        "link_domain": "bankujesz.pl",
        "is_main_domain": true,
        "anchor": "ranking kont oszczędnościowych sierpień 2023",
        "anchor_type": [],
        "count": {
          "count": 1,
          "percent_of_total": 0.00016396130513198886
        },
        "domains_with_anchor_count": 1,
        "anchors_uniq_count": 1,
        "percent_of_total": 0.00016396130513198886
      },
      {
        "link_domain": "bankujesz.pl",
        "is_main_domain": true,
        "anchor": "https://bankujesz.pl/podstawowe-informacje-o-nest-bank/",
        "anchor_type": [
          "naked"
        ],
        "count": {
          "count": 1,
          "percent_of_total": 0.00016396130513198886
        },
        "domains_with_anchor_count": 1,
        "anchors_uniq_count": 1,
        "percent_of_total": 0.00016396130513198886
      },
      {
        "link_domain": "bankujesz.pl",
        "is_main_domain": true,
        "anchor": "https://www.bankujesz.pl/jak-kupic-akcje-czym-sa-akcje-obligacje-papiery-wartosciowe-od-czego-zaczac-inwestowanie-gielda/",
        "anchor_type": [
          "naked"
        ],
        "count": {
          "count": 1,
          "percent_of_total": 0.00016396130513198886
        },
        "domains_with_anchor_count": 1,
        "anchors_uniq_count": 1,
        "percent_of_total": 0.00016396130513198886
      },
      {
        "link_domain": "bankujesz.pl",
        "is_main_domain": true,
        "anchor": "Kredyt gotówkowy Raiffeisen Digital Bank",
        "anchor_type": [],
        "count": {
          "count": 1,
          "percent_of_total": 0.00016396130513198886
        },
        "domains_with_anchor_count": 1,
        "anchors_uniq_count": 1,
        "percent_of_total": 0.00016396130513198886
      },
      {
        "link_domain": "bankujesz.pl",
        "is_main_domain": true,
        "anchor": "https://bankujesz.pl/news/ciekawostki-na...ior-banku/",
        "anchor_type": [],
        "count": {
          "count": 1,
          "percent_of_total": 0.00016396130513198886
        },
        "domains_with_anchor_count": 1,
        "anchors_uniq_count": 1,
        "percent_of_total": 0.00016396130513198886
      },
      {
        "link_domain": "bankujesz.pl",
        "is_main_domain": true,
        "anchor": "Kredyty",
        "anchor_type": [],
        "count": {
          "count": 1,
          "percent_of_total": 0.00016396130513198886
        },
        "domains_with_anchor_count": 1,
        "anchors_uniq_count": 1,
        "percent_of_total": 0.00016396130513198886
      },
      {
        "link_domain": "bankujesz.pl",
        "is_main_domain": true,
        "anchor": "broker Forex",
        "anchor_type": [],
        "count": {
          "count": 1,
          "percent_of_total": 0.00016396130513198886
        },
        "domains_with_anchor_count": 1,
        "anchors_uniq_count": 1,
        "percent_of_total": 0.00016396130513198886
      },
      {
        "link_domain": "bankujesz.pl",
        "is_main_domain": true,
        "anchor": "Miejsce 3 Konto Oszczędnościowe Profit",
        "anchor_type": [],
        "count": {
          "count": 1,
          "percent_of_total": 0.00016396130513198886
        },
        "domains_with_anchor_count": 1,
        "anchors_uniq_count": 1,
        "percent_of_total": 0.00016396130513198886
      },
      {
        "link_domain": "bankujesz.pl",
        "is_main_domain": true,
        "anchor": "Pekao S.A",
        "anchor_type": [],
        "count": {
          "count": 1,
          "percent_of_total": 0.00016396130513198886
        },
        "domains_with_anchor_count": 1,
        "anchors_uniq_count": 1,
        "percent_of_total": 0.00016396130513198886
      },
      {
        "link_domain": "bankujesz.pl",
        "is_main_domain": true,
        "anchor": "Miejsce 2 Lokata 3 miesięczna Velo Bank",
        "anchor_type": [],
        "count": {
          "count": 1,
          "percent_of_total": 0.00016396130513198886
        },
        "domains_with_anchor_count": 1,
        "anchors_uniq_count": 1,
        "percent_of_total": 0.00016396130513198886
      },
      {
        "link_domain": "bankujesz.pl",
        "is_main_domain": true,
        "anchor": "Kredyt gotówkowy BNP Paribas",
        "anchor_type": [],
        "count": {
          "count": 1,
          "percent_of_total": 0.00016396130513198886
        },
        "domains_with_anchor_count": 1,
        "anchors_uniq_count": 1,
        "percent_of_total": 0.00016396130513198886
      },
      {
        "link_domain": "bankujesz.pl",
        "is_main_domain": true,
        "anchor": "Miejsce 3 Lokata 3 miesięczna Bank Nowy",
        "anchor_type": [],
        "count": {
          "count": 1,
          "percent_of_total": 0.00016396130513198886
        },
        "domains_with_anchor_count": 1,
        "anchors_uniq_count": 1,
        "percent_of_total": 0.00016396130513198886
      },
      {
        "link_domain": "bankujesz.pl",
        "is_main_domain": true,
        "anchor": "Miejsce 2 Konto Oszczędnościowe Nest Bank",
        "anchor_type": [],
        "count": {
          "count": 1,
          "percent_of_total": 0.00016396130513198886
        },
        "domains_with_anchor_count": 1,
        "anchors_uniq_count": 1,
        "percent_of_total": 0.00016396130513198886
      },
      {
        "link_domain": "bankujesz.pl",
        "is_main_domain": true,
        "anchor": "Ranking giełd kryptowalut grudzień 2023",
        "anchor_type": [],
        "count": {
          "count": 1,
          "percent_of_total": 0.00016396130513198886
        },
        "domains_with_anchor_count": 1,
        "anchors_uniq_count": 1,
        "percent_of_total": 0.00016396130513198886
      },
      {
        "link_domain": "bankujesz.pl",
        "is_main_domain": true,
        "anchor": "https://bankujesz.pl/bnp-paribas-bank-polska/",
        "anchor_type": [
          "naked"
        ],
        "count": {
          "count": 1,
          "percent_of_total": 0.00016396130513198886
        },
        "domains_with_anchor_count": 1,
        "anchors_uniq_count": 1,
        "percent_of_total": 0.00016396130513198886
      },
      {
        "link_domain": "bankujesz.pl",
        "is_main_domain": true,
        "anchor": "Citi Handlowy karta kredytowa 2023",
        "anchor_type": [],
        "count": {
          "count": 1,
          "percent_of_total": 0.00016396130513198886
        },
        "domains_with_anchor_count": 1,
        "anchors_uniq_count": 1,
        "percent_of_total": 0.00016396130513198886
      },
      {
        "link_domain": "bankujesz.pl",
        "is_main_domain": true,
        "anchor": "Giełda Kryptowalut Binance",
        "anchor_type": [],
        "count": {
          "count": 1,
          "percent_of_total": 0.00016396130513198886
        },
        "domains_with_anchor_count": 1,
        "anchors_uniq_count": 1,
        "percent_of_total": 0.00016396130513198886
      },
      {
        "link_domain": "bankujesz.pl",
        "is_main_domain": true,
        "anchor": "mBank",
        "anchor_type": [],
        "count": {
          "count": 1,
          "percent_of_total": 0.00016396130513198886
        },
        "domains_with_anchor_count": 1,
        "anchors_uniq_count": 1,
        "percent_of_total": 0.00016396130513198886
      },
      {
        "link_domain": "bankujesz.pl",
        "is_main_domain": true,
        "anchor": "Santander karta kredytowa wrzesień 2023",
        "anchor_type": [],
        "count": {
          "count": 1,
          "percent_of_total": 0.00016396130513198886
        },
        "domains_with_anchor_count": 1,
        "anchors_uniq_count": 1,
        "percent_of_total": 0.00016396130513198886
      },
      {
        "link_domain": "bankujesz.pl",
        "is_main_domain": true,
        "anchor": "Giełda Kryptowalut Zonda",
        "anchor_type": [],
        "count": {
          "count": 1,
          "percent_of_total": 0.00016396130513198886
        },
        "domains_with_anchor_count": 1,
        "anchors_uniq_count": 1,
        "percent_of_total": 0.00016396130513198886
      }
    ],
    "total": 240,
    "domain": "bankujesz.pl",
    "endpoint": "get_backlinks_anchor_data"
  }
}