{
  "domain": "podzastaw.biz",
  "endpoint": "get_backlinks_anchor_data",
  "data": {
    "ok": true,
    "data": [
      {
        "link_domain": "podzastaw.biz",
        "is_main_domain": true,
        "anchor": "Mr Kocur",
        "anchor_type": [],
        "count": {
          "count": 101,
          "percent_of_total": 0.3686131386861314
        },
        "domains_with_anchor_count": 4,
        "anchors_uniq_count": 101,
        "percent_of_total": 0.3686131386861314
      },
      {
        "link_domain": "podzastaw.biz",
        "is_main_domain": true,
        "anchor": "Strona",
        "anchor_type": [],
        "count": {
          "count": 22,
          "percent_of_total": 0.08029197080291971
        },
        "domains_with_anchor_count": 2,
        "anchors_uniq_count": 22,
        "percent_of_total": 0.08029197080291971
      },
      {
        "link_domain": "podzastaw.biz",
        "is_main_domain": true,
        "anchor": "szybkie pożyczki pod zastaw firmowej nieruchomości",
        "anchor_type": [],
        "count": {
          "count": 20,
          "percent_of_total": 0.072992700729927
        },
        "domains_with_anchor_count": 1,
        "anchors_uniq_count": 9,
        "percent_of_total": 0.072992700729927
      },
      {
        "link_domain": "podzastaw.biz",
        "is_main_domain": true,
        "anchor": "https://podzastaw.biz",
        "anchor_type": [],
        "count": {
          "count": 10,
          "percent_of_total": 0.0364963503649635
        },
        "domains_with_anchor_count": 8,
        "anchors_uniq_count": 8,
        "percent_of_total": 0.0364963503649635
      },
      {
        "link_domain": "podzastaw.biz",
        "is_main_domain": true,
        "anchor": "PodZastaw.biz",
        "anchor_type": [],
        "count": {
          "count": 7,
          "percent_of_total": 0.025547445255474453
        },
        "domains_with_anchor_count": 5,
        "anchors_uniq_count": 5,
        "percent_of_total": 0.025547445255474453
      },
      {
        "link_domain": "podzastaw.biz",
        "is_main_domain": true,
        "anchor": "~Mr Kocur",
        "anchor_type": [],
        "count": {
          "count": 6,
          "percent_of_total": 0.021897810218978103
        },
        "domains_with_anchor_count": 5,
        "anchors_uniq_count": 5,
        "percent_of_total": 0.021897810218978103
      },
      {
        "link_domain": "podzastaw.biz",
        "is_main_domain": true,
        "anchor": "funkcjonalna pożyczka dla firmy pod zastaw domu bez BIK",
        "anchor_type": [],
        "count": {
          "count": 4,
          "percent_of_total": 0.014598540145985401
        },
        "domains_with_anchor_count": 1,
        "anchors_uniq_count": 1,
        "percent_of_total": 0.014598540145985401
      },
      {
        "link_domain": "podzastaw.biz",
        "is_main_domain": true,
        "anchor": "pilne pozabankowe finansowanie pod zastaw nieruchomości",
        "anchor_type": [],
        "count": {
          "count": 3,
          "percent_of_total": 0.010948905109489052
        },
        "domains_with_anchor_count": 1,
        "anchors_uniq_count": 1,
        "percent_of_total": 0.010948905109489052
      },
      {
        "link_domain": "podzastaw.biz",
        "is_main_domain": true,
        "anchor": "WWW",
        "anchor_type": [],
        "count": {
          "count": 3,
          "percent_of_total": 0.010948905109489052
        },
        "domains_with_anchor_count": 2,
        "anchors_uniq_count": 3,
        "percent_of_total": 0.010948905109489052
      },
      {
        "link_domain": "podzastaw.biz",
        "is_main_domain": true,
        "anchor": "priorytetowo poszukiwana pożyczka pod zastaw nieruchomości bez BIK",
        "anchor_type": [],
        "count": {
          "count": 3,
          "percent_of_total": 0.010948905109489052
        },
        "domains_with_anchor_count": 1,
        "anchors_uniq_count": 1,
        "percent_of_total": 0.010948905109489052
      },
      {
        "link_domain": "podzastaw.biz",
        "is_main_domain": true,
        "anchor": "https://podzastaw.biz/",
        "anchor_type": [
          "naked"
        ],
        "count": {
          "count": 2,
          "percent_of_total": 0.0072992700729927005
        },
        "domains_with_anchor_count": 2,
        "anchors_uniq_count": 2,
        "percent_of_total": 0.0072992700729927005
      },
      {
        "link_domain": "podzastaw.biz",
        "is_main_domain": true,
        "anchor": "pełnowartościowa prywatna pożyczka pod zastaw nieruchomości na cele biznesowe",
        "anchor_type": [],
        "count": {
          "count": 2,
          "percent_of_total": 0.0072992700729927005
        },
        "domains_with_anchor_count": 1,
        "anchors_uniq_count": 1,
        "percent_of_total": 0.0072992700729927005
      },
      {
        "link_domain": "podzastaw.biz",
        "is_main_domain": true,
        "anchor": "pomocne wskazówki",
        "anchor_type": [],
        "count": {
          "count": 2,
          "percent_of_total": 0.0072992700729927005
        },
        "domains_with_anchor_count": 1,
        "anchors_uniq_count": 1,
        "percent_of_total": 0.0072992700729927005
      },
      {
        "link_domain": "podzastaw.biz",
        "is_main_domain": true,
        "anchor": "godna polecenia pożyczka pod nieruchomość",
        "anchor_type": [],
        "count": {
          "count": 2,
          "percent_of_total": 0.0072992700729927005
        },
        "domains_with_anchor_count": 1,
        "anchors_uniq_count": 1,
        "percent_of_total": 0.0072992700729927005
      },
      {
        "link_domain": "podzastaw.biz",
        "is_main_domain": true,
        "anchor": "Obrazek",
        "anchor_type": [
          "multimedia"
        ],
        "count": {
          "count": 2,
          "percent_of_total": 0.0072992700729927005
        },
        "domains_with_anchor_count": 1,
        "anchors_uniq_count": 2,
        "percent_of_total": 0.0072992700729927005
      },
      {
        "link_domain": "podzastaw.biz",
        "is_main_domain": true,
        "anchor": "przedsiębiorcy mogą ubiegać się o pożyczki pod zastaw nieruchomości bez BIK",
        "anchor_type": [],
        "count": {
          "count": 2,
          "percent_of_total": 0.0072992700729927005
        },
        "domains_with_anchor_count": 1,
        "anchors_uniq_count": 1,
        "percent_of_total": 0.0072992700729927005
      },
      {
        "link_domain": "podzastaw.biz",
        "is_main_domain": true,
        "anchor": "Dogodna dla firmy pożyczka pod mieszkanie",
        "anchor_type": [],
        "count": {
          "count": 2,
          "percent_of_total": 0.0072992700729927005
        },
        "domains_with_anchor_count": 1,
        "anchors_uniq_count": 1,
        "percent_of_total": 0.0072992700729927005
      },
      {
        "link_domain": "podzastaw.biz",
        "is_main_domain": true,
        "anchor": "interesujący wpis",
        "anchor_type": [],
        "count": {
          "count": 2,
          "percent_of_total": 0.0072992700729927005
        },
        "domains_with_anchor_count": 1,
        "anchors_uniq_count": 1,
        "percent_of_total": 0.0072992700729927005
      },
      {
        "link_domain": "podzastaw.biz",
        "is_main_domain": true,
        "anchor": "profesjonalne pożyczki prywatne pod zastaw nieruchomości dla firm",
        "anchor_type": [],
        "count": {
          "count": 2,
          "percent_of_total": 0.0072992700729927005
        },
        "domains_with_anchor_count": 1,
        "anchors_uniq_count": 1,
        "percent_of_total": 0.0072992700729927005
      },
      {
        "link_domain": "podzastaw.biz",
        "is_main_domain": true,
        "anchor": "pożyczki pod zastaw",
        "anchor_type": [],
        "count": {
          "count": 2,
          "percent_of_total": 0.0072992700729927005
        },
        "domains_with_anchor_count": 1,
        "anchors_uniq_count": 1,
        "percent_of_total": 0.0072992700729927005
      },
      {
        "link_domain": "podzastaw.biz",
        "is_main_domain": true,
        "anchor": "sprawdzić na stronie: https://podzastaw.biz",
        "anchor_type": [],
        "count": {
          "count": 2,
          "percent_of_total": 0.0072992700729927005
        },
        "domains_with_anchor_count": 1,
        "anchors_uniq_count": 1,
        "percent_of_total": 0.0072992700729927005
      },
      {
        "link_domain": "podzastaw.biz",
        "is_main_domain": true,
        "anchor": "pożyczka pod zastaw nieruchomości lub środków transportu",
        "anchor_type": [],
        "count": {
          "count": 2,
          "percent_of_total": 0.0072992700729927005
        },
        "domains_with_anchor_count": 1,
        "anchors_uniq_count": 1,
        "percent_of_total": 0.0072992700729927005
      },
      {
        "link_domain": "podzastaw.biz",
        "is_main_domain": true,
        "anchor": "pożyczka pod zastaw nieruchomości daje firmie więcej możliwości",
        "anchor_type": [],
        "count": {
          "count": 2,
          "percent_of_total": 0.0072992700729927005
        },
        "domains_with_anchor_count": 1,
        "anchors_uniq_count": 1,
        "percent_of_total": 0.0072992700729927005
      },
      {
        "link_domain": "podzastaw.biz",
        "is_main_domain": true,
        "anchor": "dla firmy pożyczka pod zastaw działki",
        "anchor_type": [],
        "count": {
          "count": 2,
          "percent_of_total": 0.0072992700729927005
        },
        "domains_with_anchor_count": 1,
        "anchors_uniq_count": 1,
        "percent_of_total": 0.0072992700729927005
      },
      {
        "link_domain": "podzastaw.biz",
        "is_main_domain": true,
        "anchor": "Bardzo wygodna pożyczka pod zastaw ziemi",
        "anchor_type": [],
        "count": {
          "count": 2,
          "percent_of_total": 0.0072992700729927005
        },
        "domains_with_anchor_count": 1,
        "anchors_uniq_count": 1,
        "percent_of_total": 0.0072992700729927005
      },
      {
        "link_domain": "podzastaw.biz",
        "is_main_domain": true,
        "anchor": "pożyczka pozabankowa pod zastaw nieruchomości dla małej firmy",
        "anchor_type": [],
        "count": {
          "count": 2,
          "percent_of_total": 0.0072992700729927005
        },
        "domains_with_anchor_count": 1,
        "anchors_uniq_count": 1,
        "percent_of_total": 0.0072992700729927005
      },
      {
        "link_domain": "podzastaw.biz",
        "is_main_domain": true,
        "anchor": "Więcej info",
        "anchor_type": [],
        "count": {
          "count": 2,
          "percent_of_total": 0.0072992700729927005
        },
        "domains_with_anchor_count": 1,
        "anchors_uniq_count": 1,
        "percent_of_total": 0.0072992700729927005
      },
      {
        "link_domain": "podzastaw.biz",
        "is_main_domain": true,
        "anchor": "rekomendowana pożyczka pod zastaw nieruchomości bez zdolności kredytowej",
        "anchor_type": [],
        "count": {
          "count": 2,
          "percent_of_total": 0.0072992700729927005
        },
        "domains_with_anchor_count": 1,
        "anchors_uniq_count": 1,
        "percent_of_total": 0.0072992700729927005
      },
      {
        "link_domain": "podzastaw.biz",
        "is_main_domain": true,
        "anchor": "pożyczka prywatna pod zastaw nieruchomości godna polecenia",
        "anchor_type": [],
        "count": {
          "count": 2,
          "percent_of_total": 0.0072992700729927005
        },
        "domains_with_anchor_count": 1,
        "anchors_uniq_count": 1,
        "percent_of_total": 0.0072992700729927005
      },
      {
        "link_domain": "podzastaw.biz",
        "is_main_domain": true,
        "anchor": "optymalne pożyczki pod zastaw mieszkania",
        "anchor_type": [],
        "count": {
          "count": 1,
          "percent_of_total": 0.0036496350364963502
        },
        "domains_with_anchor_count": 1,
        "anchors_uniq_count": 1,
        "percent_of_total": 0.0036496350364963502
      },
      {
        "link_domain": "podzastaw.biz",
        "is_main_domain": true,
        "anchor": "szukam pożyczki pod zastaw nieruchomości",
        "anchor_type": [],
        "count": {
          "count": 1,
          "percent_of_total": 0.0036496350364963502
        },
        "domains_with_anchor_count": 1,
        "anchors_uniq_count": 1,
        "percent_of_total": 0.0036496350364963502
      },
      {
        "link_domain": "podzastaw.biz",
        "is_main_domain": true,
        "anchor": "pożyczki pod zastaw dostępne dla małych firm",
        "anchor_type": [],
        "count": {
          "count": 1,
          "percent_of_total": 0.0036496350364963502
        },
        "domains_with_anchor_count": 1,
        "anchors_uniq_count": 1,
        "percent_of_total": 0.0036496350364963502
      },
      {
        "link_domain": "podzastaw.biz",
        "is_main_domain": true,
        "anchor": "elastyczna pożyczka pozabankowa pod zastaw mieszkania",
        "anchor_type": [],
        "count": {
          "count": 1,
          "percent_of_total": 0.0036496350364963502
        },
        "domains_with_anchor_count": 1,
        "anchors_uniq_count": 1,
        "percent_of_total": 0.0036496350364963502
      },
      {
        "link_domain": "podzastaw.biz",
        "is_main_domain": true,
        "anchor": "https://podzastaw.biz/pytania",
        "anchor_type": [
          "naked"
        ],
        "count": {
          "count": 1,
          "percent_of_total": 0.0036496350364963502
        },
        "domains_with_anchor_count": 1,
        "anchors_uniq_count": 1,
        "percent_of_total": 0.0036496350364963502
      },
      {
        "link_domain": "podzastaw.biz",
        "is_main_domain": true,
        "anchor": "godna uwagi przedsiębiorcy pożyczka pod zastaw domu",
        "anchor_type": [],
        "count": {
          "count": 1,
          "percent_of_total": 0.0036496350364963502
        },
        "domains_with_anchor_count": 1,
        "anchors_uniq_count": 1,
        "percent_of_total": 0.0036496350364963502
      },
      {
        "link_domain": "podzastaw.biz",
        "is_main_domain": true,
        "anchor": "pożyczka pod zastaw ziemi rolnej na realizację celu biznesowego",
        "anchor_type": [],
        "count": {
          "count": 1,
          "percent_of_total": 0.0036496350364963502
        },
        "domains_with_anchor_count": 1,
        "anchors_uniq_count": 1,
        "percent_of_total": 0.0036496350364963502
      },
      {
        "link_domain": "podzastaw.biz",
        "is_main_domain": true,
        "anchor": "osiągalne konkurencyjne pożyczki pod zastaw mieszkania bez BIK",
        "anchor_type": [],
        "count": {
          "count": 1,
          "percent_of_total": 0.0036496350364963502
        },
        "domains_with_anchor_count": 1,
        "anchors_uniq_count": 1,
        "percent_of_total": 0.0036496350364963502
      },
      {
        "link_domain": "podzastaw.biz",
        "is_main_domain": true,
        "anchor": "Pożyczki pod zastaw nieruchomości dla zadłużonych przedsiębiorstw",
        "anchor_type": [],
        "count": {
          "count": 1,
          "percent_of_total": 0.0036496350364963502
        },
        "domains_with_anchor_count": 1,
        "anchors_uniq_count": 1,
        "percent_of_total": 0.0036496350364963502
      },
      {
        "link_domain": "podzastaw.biz",
        "is_main_domain": true,
        "anchor": "Komfortowe pożyczki pod zastaw w domu klienta",
        "anchor_type": [],
        "count": {
          "count": 1,
          "percent_of_total": 0.0036496350364963502
        },
        "domains_with_anchor_count": 1,
        "anchors_uniq_count": 1,
        "percent_of_total": 0.0036496350364963502
      },
      {
        "link_domain": "podzastaw.biz",
        "is_main_domain": true,
        "anchor": "Więcej wskazówek",
        "anchor_type": [],
        "count": {
          "count": 1,
          "percent_of_total": 0.0036496350364963502
        },
        "domains_with_anchor_count": 1,
        "anchors_uniq_count": 1,
        "percent_of_total": 0.0036496350364963502
      },
      {
        "link_domain": "podzastaw.biz",
        "is_main_domain": true,
        "anchor": "Szybka pożyczka pod zastaw mieszkania własnościowego",
        "anchor_type": [],
        "count": {
          "count": 1,
          "percent_of_total": 0.0036496350364963502
        },
        "domains_with_anchor_count": 1,
        "anchors_uniq_count": 1,
        "percent_of_total": 0.0036496350364963502
      },
      {
        "link_domain": "podzastaw.biz",
        "is_main_domain": true,
        "anchor": "pożyczki pod zastaw nie narzucają ograniczeń",
        "anchor_type": [],
        "count": {
          "count": 1,
          "percent_of_total": 0.0036496350364963502
        },
        "domains_with_anchor_count": 1,
        "anchors_uniq_count": 1,
        "percent_of_total": 0.0036496350364963502
      },
      {
        "link_domain": "podzastaw.biz",
        "is_main_domain": true,
        "anchor": "adekwatne pożyczki pod zabezpieczenie dla firm",
        "anchor_type": [],
        "count": {
          "count": 1,
          "percent_of_total": 0.0036496350364963502
        },
        "domains_with_anchor_count": 1,
        "anchors_uniq_count": 1,
        "percent_of_total": 0.0036496350364963502
      },
      {
        "link_domain": "podzastaw.biz",
        "is_main_domain": true,
        "anchor": "elastyczna pożyczka pod zastaw mieszkania dla firmy bądź osoby prywatnej",
        "anchor_type": [],
        "count": {
          "count": 1,
          "percent_of_total": 0.0036496350364963502
        },
        "domains_with_anchor_count": 1,
        "anchors_uniq_count": 1,
        "percent_of_total": 0.0036496350364963502
      },
      {
        "link_domain": "podzastaw.biz",
        "is_main_domain": true,
        "anchor": "pożyczka dostępna jest pod zastaw gruntów rolnych",
        "anchor_type": [],
        "count": {
          "count": 1,
          "percent_of_total": 0.0036496350364963502
        },
        "domains_with_anchor_count": 1,
        "anchors_uniq_count": 1,
        "percent_of_total": 0.0036496350364963502
      },
      {
        "link_domain": "podzastaw.biz",
        "is_main_domain": true,
        "anchor": "atrakcyjnie oprocentowane pożyczki pod zastaw nieruchomości",
        "anchor_type": [],
        "count": {
          "count": 1,
          "percent_of_total": 0.0036496350364963502
        },
        "domains_with_anchor_count": 1,
        "anchors_uniq_count": 1,
        "percent_of_total": 0.0036496350364963502
      },
      {
        "link_domain": "podzastaw.biz",
        "is_main_domain": true,
        "anchor": "pożyczka pod zastaw domu na cele biznesowe",
        "anchor_type": [],
        "count": {
          "count": 1,
          "percent_of_total": 0.0036496350364963502
        },
        "domains_with_anchor_count": 1,
        "anchors_uniq_count": 1,
        "percent_of_total": 0.0036496350364963502
      },
      {
        "link_domain": "podzastaw.biz",
        "is_main_domain": true,
        "anchor": "na cele biznesowe pożyczki pod zastaw nieruchomości pozabankowe i niezwłoczne",
        "anchor_type": [],
        "count": {
          "count": 1,
          "percent_of_total": 0.0036496350364963502
        },
        "domains_with_anchor_count": 1,
        "anchors_uniq_count": 1,
        "percent_of_total": 0.0036496350364963502
      },
      {
        "link_domain": "podzastaw.biz",
        "is_main_domain": true,
        "anchor": "w serwisie https://podzastaw.biz",
        "anchor_type": [],
        "count": {
          "count": 1,
          "percent_of_total": 0.0036496350364963502
        },
        "domains_with_anchor_count": 1,
        "anchors_uniq_count": 1,
        "percent_of_total": 0.0036496350364963502
      },
      {
        "link_domain": "podzastaw.biz",
        "is_main_domain": true,
        "anchor": "podzastaw.biz",
        "anchor_type": [],
        "count": {
          "count": 1,
          "percent_of_total": 0.0036496350364963502
        },
        "domains_with_anchor_count": 1,
        "anchors_uniq_count": 1,
        "percent_of_total": 0.0036496350364963502
      },
      {
        "link_domain": "podzastaw.biz",
        "is_main_domain": true,
        "anchor": "dost",
        "anchor_type": [],
        "count": {
          "count": 1,
          "percent_of_total": 0.0036496350364963502
        },
        "domains_with_anchor_count": 1,
        "anchors_uniq_count": 1,
        "percent_of_total": 0.0036496350364963502
      },
      {
        "link_domain": "podzastaw.biz",
        "is_main_domain": true,
        "anchor": "pożyczką prywatną pod zastaw firmowej nieruchomości",
        "anchor_type": [],
        "count": {
          "count": 1,
          "percent_of_total": 0.0036496350364963502
        },
        "domains_with_anchor_count": 1,
        "anchors_uniq_count": 1,
        "percent_of_total": 0.0036496350364963502
      },
      {
        "link_domain": "podzastaw.biz",
        "is_main_domain": true,
        "anchor": "bezpieczne czyli skrupulatnie kalkulowane pożyczki pod zastaw nieruchomości",
        "anchor_type": [],
        "count": {
          "count": 1,
          "percent_of_total": 0.0036496350364963502
        },
        "domains_with_anchor_count": 1,
        "anchors_uniq_count": 1,
        "percent_of_total": 0.0036496350364963502
      },
      {
        "link_domain": "podzastaw.biz",
        "is_main_domain": true,
        "anchor": "elastycznych pożyczek bez&nbsp;badania BIK pod&nbsp;zastaw nieruchomości",
        "anchor_type": [],
        "count": {
          "count": 1,
          "percent_of_total": 0.0036496350364963502
        },
        "domains_with_anchor_count": 1,
        "anchors_uniq_count": 1,
        "percent_of_total": 0.0036496350364963502
      },
      {
        "link_domain": "podzastaw.biz",
        "is_main_domain": true,
        "anchor": "pomyśleć nad pożyczką pod zastaw nieruchomości bez weryfikacji BIK",
        "anchor_type": [],
        "count": {
          "count": 1,
          "percent_of_total": 0.0036496350364963502
        },
        "domains_with_anchor_count": 1,
        "anchors_uniq_count": 1,
        "percent_of_total": 0.0036496350364963502
      },
      {
        "link_domain": "podzastaw.biz",
        "is_main_domain": true,
        "anchor": "pożyczki pod zastaw nieruchomości pozabankowe i niedrogie",
        "anchor_type": [],
        "count": {
          "count": 1,
          "percent_of_total": 0.0036496350364963502
        },
        "domains_with_anchor_count": 1,
        "anchors_uniq_count": 1,
        "percent_of_total": 0.0036496350364963502
      },
      {
        "link_domain": "podzastaw.biz",
        "is_main_domain": true,
        "anchor": "pożyczki pod zastaw nieruchomości i środków transportu",
        "anchor_type": [],
        "count": {
          "count": 1,
          "percent_of_total": 0.0036496350364963502
        },
        "domains_with_anchor_count": 1,
        "anchors_uniq_count": 1,
        "percent_of_total": 0.0036496350364963502
      },
      {
        "link_domain": "podzastaw.biz",
        "is_main_domain": true,
        "anchor": "odpowiednie do sytuacji pożyczki pod zastaw nieruchomości",
        "anchor_type": [],
        "count": {
          "count": 1,
          "percent_of_total": 0.0036496350364963502
        },
        "domains_with_anchor_count": 1,
        "anchors_uniq_count": 1,
        "percent_of_total": 0.0036496350364963502
      },
      {
        "link_domain": "podzastaw.biz",
        "is_main_domain": true,
        "anchor": "procesu uzyskiwania pożyczki pod zastaw",
        "anchor_type": [],
        "count": {
          "count": 1,
          "percent_of_total": 0.0036496350364963502
        },
        "domains_with_anchor_count": 1,
        "anchors_uniq_count": 1,
        "percent_of_total": 0.0036496350364963502
      },
      {
        "link_domain": "podzastaw.biz",
        "is_main_domain": true,
        "anchor": "https://podzastaw.biz/pozyczka-pod-zastaw-domu",
        "anchor_type": [
          "naked"
        ],
        "count": {
          "count": 1,
          "percent_of_total": 0.0036496350364963502
        },
        "domains_with_anchor_count": 1,
        "anchors_uniq_count": 1,
        "percent_of_total": 0.0036496350364963502
      },
      {
        "link_domain": "podzastaw.biz",
        "is_main_domain": true,
        "anchor": "pożyczka dla firmy z komornikiem jest możliwa pod zastaw nieruchomości",
        "anchor_type": [],
        "count": {
          "count": 1,
          "percent_of_total": 0.0036496350364963502
        },
        "domains_with_anchor_count": 1,
        "anchors_uniq_count": 1,
        "percent_of_total": 0.0036496350364963502
      },
      {
        "link_domain": "podzastaw.biz",
        "is_main_domain": true,
        "anchor": "dostępne i szybkie finansowanie pod zastaw nieruchomości bez BIK",
        "anchor_type": [],
        "count": {
          "count": 1,
          "percent_of_total": 0.0036496350364963502
        },
        "domains_with_anchor_count": 1,
        "anchors_uniq_count": 1,
        "percent_of_total": 0.0036496350364963502
      },
      {
        "link_domain": "podzastaw.biz",
        "is_main_domain": true,
        "anchor": "szukasz bezpiecznej pożyczki pod zastaw nieruchomości",
        "anchor_type": [],
        "count": {
          "count": 1,
          "percent_of_total": 0.0036496350364963502
        },
        "domains_with_anchor_count": 1,
        "anchors_uniq_count": 1,
        "percent_of_total": 0.0036496350364963502
      },
      {
        "link_domain": "podzastaw.biz",
        "is_main_domain": true,
        "anchor": "pożyczki pod zastaw dodatkowe źródło finansowania",
        "anchor_type": [],
        "count": {
          "count": 1,
          "percent_of_total": 0.0036496350364963502
        },
        "domains_with_anchor_count": 1,
        "anchors_uniq_count": 1,
        "percent_of_total": 0.0036496350364963502
      },
      {
        "link_domain": "podzastaw.biz",
        "is_main_domain": true,
        "anchor": "pożyczka pod zastaw domu bez BIK oraz innych baz",
        "anchor_type": [],
        "count": {
          "count": 1,
          "percent_of_total": 0.0036496350364963502
        },
        "domains_with_anchor_count": 1,
        "anchors_uniq_count": 1,
        "percent_of_total": 0.0036496350364963502
      },
      {
        "link_domain": "podzastaw.biz",
        "is_main_domain": true,
        "anchor": "szybko wypłacona pożyczka pod zastaw mieszkania",
        "anchor_type": [],
        "count": {
          "count": 1,
          "percent_of_total": 0.0036496350364963502
        },
        "domains_with_anchor_count": 1,
        "anchors_uniq_count": 1,
        "percent_of_total": 0.0036496350364963502
      },
      {
        "link_domain": "podzastaw.biz",
        "is_main_domain": true,
        "anchor": "proces uzyskania pożyczki pod zastaw nieruchomości może być stosunkowo szybki",
        "anchor_type": [],
        "count": {
          "count": 1,
          "percent_of_total": 0.0036496350364963502
        },
        "domains_with_anchor_count": 1,
        "anchors_uniq_count": 1,
        "percent_of_total": 0.0036496350364963502
      },
      {
        "link_domain": "podzastaw.biz",
        "is_main_domain": true,
        "anchor": "działki budowlane mogą służyć jako zabezpieczenie pożyczki",
        "anchor_type": [],
        "count": {
          "count": 1,
          "percent_of_total": 0.0036496350364963502
        },
        "domains_with_anchor_count": 1,
        "anchors_uniq_count": 1,
        "percent_of_total": 0.0036496350364963502
      },
      {
        "link_domain": "podzastaw.biz",
        "is_main_domain": true,
        "anchor": "Komfortowa pożyczka pod zastaw dużej działki budowlanej",
        "anchor_type": [],
        "count": {
          "count": 1,
          "percent_of_total": 0.0036496350364963502
        },
        "domains_with_anchor_count": 1,
        "anchors_uniq_count": 1,
        "percent_of_total": 0.0036496350364963502
      },
      {
        "link_domain": "podzastaw.biz",
        "is_main_domain": true,
        "anchor": "pożyczki pod zastaw nieruchomości z komornikiem dla firm",
        "anchor_type": [],
        "count": {
          "count": 1,
          "percent_of_total": 0.0036496350364963502
        },
        "domains_with_anchor_count": 1,
        "anchors_uniq_count": 1,
        "percent_of_total": 0.0036496350364963502
      },
      {
        "link_domain": "podzastaw.biz",
        "is_main_domain": true,
        "anchor": "bezpieczne i elastyczne pożyczki pod nieruchomości",
        "anchor_type": [],
        "count": {
          "count": 1,
          "percent_of_total": 0.0036496350364963502
        },
        "domains_with_anchor_count": 1,
        "anchors_uniq_count": 1,
        "percent_of_total": 0.0036496350364963502
      },
      {
        "link_domain": "podzastaw.biz",
        "is_main_domain": true,
        "anchor": "pożyczka pod zastaw",
        "anchor_type": [],
        "count": {
          "count": 1,
          "percent_of_total": 0.0036496350364963502
        },
        "domains_with_anchor_count": 1,
        "anchors_uniq_count": 1,
        "percent_of_total": 0.0036496350364963502
      },
      {
        "link_domain": "podzastaw.biz",
        "is_main_domain": true,
        "anchor": "Pożyczki dla firm pod&nbsp;zastaw nieruchomości opierają się na&nbsp;zabezpieczeniu",
        "anchor_type": [],
        "count": {
          "count": 1,
          "percent_of_total": 0.0036496350364963502
        },
        "domains_with_anchor_count": 1,
        "anchors_uniq_count": 1,
        "percent_of_total": 0.0036496350364963502
      },
      {
        "link_domain": "podzastaw.biz",
        "is_main_domain": true,
        "anchor": "dostępne pożyczki pod zastaw nieruchomości pozabankowe",
        "anchor_type": [],
        "count": {
          "count": 1,
          "percent_of_total": 0.0036496350364963502
        },
        "domains_with_anchor_count": 1,
        "anchors_uniq_count": 1,
        "percent_of_total": 0.0036496350364963502
      },
      {
        "link_domain": "podzastaw.biz",
        "is_main_domain": true,
        "anchor": "pożyczka pod zastaw domu informacje i opinie online",
        "anchor_type": [],
        "count": {
          "count": 1,
          "percent_of_total": 0.0036496350364963502
        },
        "domains_with_anchor_count": 1,
        "anchors_uniq_count": 1,
        "percent_of_total": 0.0036496350364963502
      },
      {
        "link_domain": "podzastaw.biz",
        "is_main_domain": true,
        "anchor": "również pozbankowe oferujące pożyczki pod zastaw nieruchomości",
        "anchor_type": [],
        "count": {
          "count": 1,
          "percent_of_total": 0.0036496350364963502
        },
        "domains_with_anchor_count": 1,
        "anchors_uniq_count": 1,
        "percent_of_total": 0.0036496350364963502
      },
      {
        "link_domain": "podzastaw.biz",
        "is_main_domain": true,
        "anchor": "czy przyznać firmie pożyczkę pod zastaw działki",
        "anchor_type": [],
        "count": {
          "count": 1,
          "percent_of_total": 0.0036496350364963502
        },
        "domains_with_anchor_count": 1,
        "anchors_uniq_count": 1,
        "percent_of_total": 0.0036496350364963502
      },
      {
        "link_domain": "podzastaw.biz",
        "is_main_domain": true,
        "anchor": "Więcej informacji",
        "anchor_type": [],
        "count": {
          "count": 1,
          "percent_of_total": 0.0036496350364963502
        },
        "domains_with_anchor_count": 1,
        "anchors_uniq_count": 1,
        "percent_of_total": 0.0036496350364963502
      },
      {
        "link_domain": "podzastaw.biz",
        "is_main_domain": true,
        "anchor": "interesująca pozabankowa pożyczka pod zastaw nieruchomości dla zaradnych przedsiębiorców",
        "anchor_type": [],
        "count": {
          "count": 1,
          "percent_of_total": 0.0036496350364963502
        },
        "domains_with_anchor_count": 1,
        "anchors_uniq_count": 1,
        "percent_of_total": 0.0036496350364963502
      },
      {
        "link_domain": "podzastaw.biz",
        "is_main_domain": true,
        "anchor": "jest możliwość udzielenia pożyczki pod zastaw",
        "anchor_type": [],
        "count": {
          "count": 1,
          "percent_of_total": 0.0036496350364963502
        },
        "domains_with_anchor_count": 1,
        "anchors_uniq_count": 1,
        "percent_of_total": 0.0036496350364963502
      },
      {
        "link_domain": "podzastaw.biz",
        "is_main_domain": true,
        "anchor": "właściwa pożyczka pozabankowa pod zastaw nieruchomości dla biznesu",
        "anchor_type": [],
        "count": {
          "count": 1,
          "percent_of_total": 0.0036496350364963502
        },
        "domains_with_anchor_count": 1,
        "anchors_uniq_count": 1,
        "percent_of_total": 0.0036496350364963502
      },
      {
        "link_domain": "podzastaw.biz",
        "is_main_domain": true,
        "anchor": "indywidualny koszt pozabankowej pożyczki pod zastaw dla firmy",
        "anchor_type": [],
        "count": {
          "count": 1,
          "percent_of_total": 0.0036496350364963502
        },
        "domains_with_anchor_count": 1,
        "anchors_uniq_count": 1,
        "percent_of_total": 0.0036496350364963502
      },
      {
        "link_domain": "podzastaw.biz",
        "is_main_domain": true,
        "anchor": "możliwa jest pożyczka pod zastaw nieruchomości bez BIK i innych baz",
        "anchor_type": [],
        "count": {
          "count": 1,
          "percent_of_total": 0.0036496350364963502
        },
        "domains_with_anchor_count": 1,
        "anchors_uniq_count": 1,
        "percent_of_total": 0.0036496350364963502
      },
      {
        "link_domain": "podzastaw.biz",
        "is_main_domain": true,
        "anchor": "Efektywna pożyczka pod zastaw",
        "anchor_type": [],
        "count": {
          "count": 1,
          "percent_of_total": 0.0036496350364963502
        },
        "domains_with_anchor_count": 1,
        "anchors_uniq_count": 1,
        "percent_of_total": 0.0036496350364963502
      },
      {
        "link_domain": "podzastaw.biz",
        "is_main_domain": true,
        "anchor": "wykorzystać pozabankową pożyczkę pod zastaw nieruchomości jako rozwiązanie pomostowe",
        "anchor_type": [],
        "count": {
          "count": 1,
          "percent_of_total": 0.0036496350364963502
        },
        "domains_with_anchor_count": 1,
        "anchors_uniq_count": 1,
        "percent_of_total": 0.0036496350364963502
      },
      {
        "link_domain": "podzastaw.biz",
        "is_main_domain": true,
        "anchor": "optymalne i tanie pożyczki pod zastaw",
        "anchor_type": [],
        "count": {
          "count": 1,
          "percent_of_total": 0.0036496350364963502
        },
        "domains_with_anchor_count": 1,
        "anchors_uniq_count": 1,
        "percent_of_total": 0.0036496350364963502
      }
    ],
    "total": 86,
    "domain": "podzastaw.biz",
    "endpoint": "get_backlinks_anchor_data"
  }
}